[{"trip_id": "14737697", "route_id": "30055", "vehicle_id": "18397", "latitude": 49.28721618652344, "longitude": -123.14178466796875, "timestamp": 1764826499, "current_stop_sequence": 1}, {"trip_id": "14680739", "route_id": "6626", "vehicle_id": "18314", "latitude": 49.28033447265625, "longitude": -123.09915161132812, "timestamp": 1764826507, "current_stop_sequence": 7}, {"trip_id": "14701070", "route_id": "16717", "vehicle_id": "9644", "latitude": 49.283668518066406, "longitude": -123.10928344726562, "timestamp": 1764826502, "current_stop_sequence": 7}, {"trip_id": "14737099", "route_id": "6616", "vehicle_id": "2194", "latitude": 49.2808837890625, "longitude": -123.13189697265625, "timestamp": 1764826499, "current_stop_sequence": 10}, {"trip_id": "14679422", "route_id": "6624", "vehicle_id": "2281", "latitude": 49.285301208496094, "longitude": -123.11611938476562, "timestamp": 1764826086, "current_stop_sequence": 10}, {"trip_id": "14736717", "route_id": "6615", "vehicle_id": "2158", "latitude": 49.283851623535156, "longitude": -123.11356353759766, "timestamp": 1764826507, "current_stop_sequence": 11}, {"trip_id": "14737101", "route_id": "6616", "vehicle_id": "2260", "latitude": 49.28089904785156, "longitude": -123.11100006103516, "timestamp": 1764826508, "current_stop_sequence": 1}, {"trip_id": "14676684", "route_id": "6620", "vehicle_id": "2541", "latitude": 49.28464889526367, "longitude": -123.11471557617188, "timestamp": 1764826501, "current_stop_sequence": 2}, {"trip_id": "14679506", "route_id": "6624", "vehicle_id": "2122", "latitude": 49.28466796875, "longitude": -123.11478424072266, "timestamp": 1764826481, "current_stop_sequence": 41}, {"trip_id": "14740962", "route_id": "6612", "vehicle_id": "21012", "latitude": 49.27866744995117, "longitude": -123.12982940673828, "timestamp": 1764826492, "current_stop_sequence": 6}, {"trip_id": "14740961", "route_id": "6612", "vehicle_id": "21010", "latitude": 49.2486686706543, "longitude": -123.16878509521484, "timestamp": 1764826488, "current_stop_sequence": 23}, {"trip_id": "14672665", "route_id": "6613", "vehicle_id": "2519", "latitude": 49.23320007324219, "longitude": -123.10143280029297, "timestamp": 1764826492, "current_stop_sequence": 12}, {"trip_id": "14679533", "route_id": "6624", "vehicle_id": "2191", "latitude": 49.26573181152344, "longitude": -123.10078430175781, "timestamp": 1764826504, "current_stop_sequence": 30}, {"trip_id": "14672666", "route_id": "6613", "vehicle_id": "2559", "latitude": 49.268768310546875, "longitude": -123.10053253173828, "timestamp": 1764826503, "current_stop_sequence": 27}, {"trip_id": "14733496", "route_id": "37810", "vehicle_id": "18004", "latitude": 49.233882904052734, "longitude": -123.12837982177734, "timestamp": 1764826493, "current_stop_sequence": 7}, {"trip_id": "14672708", "route_id": "6613", "vehicle_id": "2509", "latitude": 49.26558303833008, "longitude": -123.1009521484375, "timestamp": 1764826471, "current_stop_sequence": 11}, {"trip_id": "14672709", "route_id": "6613", "vehicle_id": "2557", "latitude": 49.232749938964844, "longitude": -123.10163116455078, "timestamp": 1764826491, "current_stop_sequence": 25}, {"trip_id": "14686567", "route_id": "6641", "vehicle_id": "22011", "latitude": 49.26431655883789, "longitude": -123.18572998046875, "timestamp": 1764826466, "current_stop_sequence": 3}, {"trip_id": "14684026", "route_id": "6633", "vehicle_id": "2259", "latitude": 49.23481750488281, "longitude": -123.1826171875, "timestamp": 1764826505, "current_stop_sequence": 44}, {"trip_id": "14674947", "route_id": "6617", "vehicle_id": "2163", "latitude": 49.238548278808594, "longitude": -123.18526458740234, "timestamp": 1764826505, "current_stop_sequence": 4}, {"trip_id": "14677029", "route_id": "16718", "vehicle_id": "2261", "latitude": 49.264183044433594, "longitude": -123.17753601074219, "timestamp": 1764826503, "current_stop_sequence": 18}, {"trip_id": "14735706", "route_id": "6619", "vehicle_id": "18348", "latitude": 49.26356887817383, "longitude": -123.14056396484375, "timestamp": 1764826505, "current_stop_sequence": 12}, {"trip_id": "14675028", "route_id": "6617", "vehicle_id": "2213", "latitude": 49.240116119384766, "longitude": -123.18533325195312, "timestamp": 1764826507, "current_stop_sequence": 62}, {"trip_id": "14683982", "route_id": "6633", "vehicle_id": "2211", "latitude": 49.234317779541016, "longitude": -123.14234924316406, "timestamp": 1764826086, "current_stop_sequence": 17}, {"trip_id": "14674946", "route_id": "6617", "vehicle_id": "2218", "latitude": 49.26788330078125, "longitude": -123.1407470703125, "timestamp": 1764826507, "current_stop_sequence": 26}, {"trip_id": "14677028", "route_id": "16718", "vehicle_id": "2205", "latitude": 49.274818420410156, "longitude": -123.12963104248047, "timestamp": 1764826488, "current_stop_sequence": 32}, {"trip_id": "14679418", "route_id": "6624", "vehicle_id": "2171", "latitude": 49.286781311035156, "longitude": -123.11994934082031, "timestamp": 1764826508, "current_stop_sequence": 9}, {"trip_id": "14677610", "route_id": "6621", "vehicle_id": "9404", "latitude": 49.26186752319336, "longitude": -123.11479949951172, "timestamp": 1764826507, "current_stop_sequence": 19}, {"trip_id": "14678247", "route_id": "6622", "vehicle_id": "2184", "latitude": 49.28139877319336, "longitude": -123.09893035888672, "timestamp": 1764826504, "current_stop_sequence": 34}, {"trip_id": "14680235", "route_id": "6625", "vehicle_id": "2558", "latitude": 49.28139877319336, "longitude": -123.09896850585938, "timestamp": 1764826492, "current_stop_sequence": 41}, {"trip_id": "14679381", "route_id": "6624", "vehicle_id": "2116", "latitude": 49.280250549316406, "longitude": -123.09974670410156, "timestamp": 1764826506, "current_stop_sequence": 16}, {"trip_id": "14676683", "route_id": "6620", "vehicle_id": "2503", "latitude": 49.25104904174805, "longitude": -123.13906860351562, "timestamp": 1764826493, "current_stop_sequence": 13}, {"trip_id": "14677169", "route_id": "16718", "vehicle_id": "2154", "latitude": 49.26435089111328, "longitude": -123.18250274658203, "timestamp": 1764826504, "current_stop_sequence": 22}, {"trip_id": "14735820", "route_id": "6619", "vehicle_id": "18349", "latitude": 49.26433181762695, "longitude": -123.18292999267578, "timestamp": 1764826242, "current_stop_sequence": 43}, {"trip_id": "14675030", "route_id": "6617", "vehicle_id": "2180", "latitude": 49.26803207397461, "longitude": -123.14181518554688, "timestamp": 1764826487, "current_stop_sequence": 39}, {"trip_id": "14677170", "route_id": "16718", "vehicle_id": "2234", "latitude": 49.268150329589844, "longitude": -123.1502685546875, "timestamp": 1764826506, "current_stop_sequence": 11}, {"trip_id": "14673260", "route_id": "6614", "vehicle_id": "2119", "latitude": 49.268733978271484, "longitude": -123.1864013671875, "timestamp": 1764826492, "current_stop_sequence": 21}, {"trip_id": "14686273", "route_id": "6638", "vehicle_id": "21001", "latitude": 49.269065856933594, "longitude": -123.21068572998047, "timestamp": 1764826484, "current_stop_sequence": 15}, {"trip_id": "14740862", "route_id": "6612", "vehicle_id": "8156", "latitude": 49.23460006713867, "longitude": -123.1857681274414, "timestamp": 1764826057, "current_stop_sequence": 1}, {"trip_id": "14733495", "route_id": "37810", "vehicle_id": "18007", "latitude": 49.23263168334961, "longitude": -123.07118225097656, "timestamp": 1764826490, "current_stop_sequence": 12}, {"trip_id": "14680236", "route_id": "6625", "vehicle_id": "2510", "latitude": 49.236331939697266, "longitude": -123.06538391113281, "timestamp": 1764826486, "current_stop_sequence": 13}, {"trip_id": "14674942", "route_id": "6617", "vehicle_id": "2252", "latitude": 49.284400939941406, "longitude": -123.05656433105469, "timestamp": 1764826506, "current_stop_sequence": 49}, {"trip_id": "14733729", "route_id": "37810", "vehicle_id": "19003", "latitude": 49.233001708984375, "longitude": -123.0913314819336, "timestamp": 1764826501, "current_stop_sequence": 7}, {"trip_id": "14675033", "route_id": "6617", "vehicle_id": "2159", "latitude": 49.26176834106445, "longitude": -123.05648040771484, "timestamp": 1764826482, "current_stop_sequence": 6}, {"trip_id": "14734337", "route_id": "37807", "vehicle_id": "19042", "latitude": 49.28123474121094, "longitude": -123.05722045898438, "timestamp": 1764826488, "current_stop_sequence": 11}, {"trip_id": "14678934", "route_id": "6623", "vehicle_id": "2276", "latitude": 49.23368453979492, "longitude": -123.1279296875, "timestamp": 1764826498, "current_stop_sequence": 15}, {"trip_id": "14675326", "route_id": "6618", "vehicle_id": "2536", "latitude": 49.26358413696289, "longitude": -123.10025024414062, "timestamp": 1764826491, "current_stop_sequence": 12}, {"trip_id": "14735705", "route_id": "6619", "vehicle_id": "18334", "latitude": 49.26276779174805, "longitude": -123.097900390625, "timestamp": 1764826498, "current_stop_sequence": 21}, {"trip_id": "14675402", "route_id": "6618", "vehicle_id": "2523", "latitude": 49.232418060302734, "longitude": -123.09068298339844, "timestamp": 1764826479, "current_stop_sequence": 31}, {"trip_id": "14679005", "route_id": "6623", "vehicle_id": "2142", "latitude": 49.21876525878906, "longitude": -123.1287841796875, "timestamp": 1764826494, "current_stop_sequence": 30}, {"trip_id": "14735822", "route_id": "6619", "vehicle_id": "18347", "latitude": 49.262901306152344, "longitude": -123.09884643554688, "timestamp": 1764826507, "current_stop_sequence": 24}, {"trip_id": "14672667", "route_id": "6613", "vehicle_id": "2555", "latitude": 49.284332275390625, "longitude": -123.11238098144531, "timestamp": 1764826487, "current_stop_sequence": 37}, {"trip_id": "14675449", "route_id": "6618", "vehicle_id": "2504", "latitude": 49.28468322753906, "longitude": -123.11298370361328, "timestamp": 1764826484, "current_stop_sequence": 42}, {"trip_id": "14677171", "route_id": "16718", "vehicle_id": "2249", "latitude": 49.28448486328125, "longitude": -123.11263275146484, "timestamp": 1764826486, "current_stop_sequence": 2}, {"trip_id": "14676635", "route_id": "6620", "vehicle_id": "2540", "latitude": 49.218666076660156, "longitude": -123.1402816772461, "timestamp": 1764826479, "current_stop_sequence": 25}, {"trip_id": "14686562", "route_id": "6641", "vehicle_id": "22012", "latitude": 49.263065338134766, "longitude": -123.02909851074219, "timestamp": 1764826476, "current_stop_sequence": 17}, {"trip_id": "14735823", "route_id": "6619", "vehicle_id": "9448", "latitude": 49.26371765136719, "longitude": -123.02825164794922, "timestamp": 1764826490, "current_stop_sequence": 1}, {"trip_id": "14735824", "route_id": "6619", "vehicle_id": "18357", "latitude": 49.265567779541016, "longitude": -123.02490234375, "timestamp": 1764826502, "current_stop_sequence": 1}, {"trip_id": "14734229", "route_id": "37807", "vehicle_id": "22005", "latitude": 49.2811164855957, "longitude": -123.03755187988281, "timestamp": 1764826490, "current_stop_sequence": 7}, {"trip_id": "14703876", "route_id": "6682", "vehicle_id": "9614", "latitude": 49.28856658935547, "longitude": -123.12788391113281, "timestamp": 1764826488, "current_stop_sequence": 36}, {"trip_id": "14678090", "route_id": "6622", "vehicle_id": "2117", "latitude": 49.213768005371094, "longitude": -123.140869140625, "timestamp": 1764826298, "current_stop_sequence": 1}, {"trip_id": "14678087", "route_id": "6622", "vehicle_id": "2231", "latitude": 49.21328353881836, "longitude": -123.14730072021484, "timestamp": 1764826487, "current_stop_sequence": 2}, {"trip_id": "14678086", "route_id": "6622", "vehicle_id": "2150", "latitude": 49.24803161621094, "longitude": -123.15312957763672, "timestamp": 1764826482, "current_stop_sequence": 20}, {"trip_id": "14678081", "route_id": "6622", "vehicle_id": "2121", "latitude": 49.266048431396484, "longitude": -123.04438018798828, "timestamp": 1764826487, "current_stop_sequence": 63}, {"trip_id": "14678251", "route_id": "6622", "vehicle_id": "2258", "latitude": 49.24413299560547, "longitude": -123.04476928710938, "timestamp": 1764826491, "current_stop_sequence": 1}, {"trip_id": "14678249", "route_id": "6622", "vehicle_id": "2280", "latitude": 49.26238250732422, "longitude": -123.0441665649414, "timestamp": 1764826487, "current_stop_sequence": 11}, {"trip_id": "14678243", "route_id": "6622", "vehicle_id": "2244", "latitude": 49.234317779541016, "longitude": -123.15567016601562, "timestamp": 1764826508, "current_stop_sequence": 63}, {"trip_id": "14679416", "route_id": "6624", "vehicle_id": "2149", "latitude": 49.24756622314453, "longitude": -123.07046508789062, "timestamp": 1764826490, "current_stop_sequence": 34}, {"trip_id": "14679364", "route_id": "6624", "vehicle_id": "2190", "latitude": 49.23586654663086, "longitude": -123.04253387451172, "timestamp": 1764826497, "current_stop_sequence": 42}, {"trip_id": "14684883", "route_id": "6636", "vehicle_id": "12002", "latitude": 49.22719955444336, "longitude": -123.0067367553711, "timestamp": 1764826030, "current_stop_sequence": 60}, {"trip_id": "14679544", "route_id": "6624", "vehicle_id": "2222", "latitude": 49.225616455078125, "longitude": -123.00274658203125, "timestamp": 1764826486, "current_stop_sequence": 1}, {"trip_id": "14679543", "route_id": "6624", "vehicle_id": "2124", "latitude": 49.23603439331055, "longitude": -123.04203033447266, "timestamp": 1764826495, "current_stop_sequence": 13}, {"trip_id": "14680293", "route_id": "6625", "vehicle_id": "2516", "latitude": 49.28081512451172, "longitude": -123.07051849365234, "timestamp": 1764826470, "current_stop_sequence": 19}, {"trip_id": "14680328", "route_id": "6625", "vehicle_id": "2574", "latitude": 49.268150329589844, "longitude": -123.06973266601562, "timestamp": 1764826491, "current_stop_sequence": 25}, {"trip_id": "14680348", "route_id": "6625", "vehicle_id": "2543", "latitude": 49.217681884765625, "longitude": -123.06598663330078, "timestamp": 1764826494, "current_stop_sequence": 48}, {"trip_id": "14680787", "route_id": "6626", "vehicle_id": "18316", "latitude": 49.21205139160156, "longitude": -123.07721710205078, "timestamp": 1764826497, "current_stop_sequence": 46}, {"trip_id": "14738243", "route_id": "6730", "vehicle_id": "9413", "latitude": 49.191932678222656, "longitude": -123.07658386230469, "timestamp": 1764826503, "current_stop_sequence": 14}, {"trip_id": "14680855", "route_id": "6626", "vehicle_id": "9449", "latitude": 49.229732513427734, "longitude": -123.07703399658203, "timestamp": 1764826496, "current_stop_sequence": 10}, {"trip_id": "14680910", "route_id": "6626", "vehicle_id": "18391", "latitude": 49.27764892578125, "longitude": -123.0969467163086, "timestamp": 1764826492, "current_stop_sequence": 35}, {"trip_id": "14692393", "route_id": "6651", "vehicle_id": "9647", "latitude": 49.28103256225586, "longitude": -123.01748657226562, "timestamp": 1764826508, "current_stop_sequence": 4}, {"trip_id": "14691332", "route_id": "6649", "vehicle_id": "9494", "latitude": 49.24995040893555, "longitude": -122.98539733886719, "timestamp": 1764826488, "current_stop_sequence": 9}, {"trip_id": "14691323", "route_id": "6649", "vehicle_id": "25146", "latitude": 49.212100982666016, "longitude": -122.92524719238281, "timestamp": 1764826482, "current_stop_sequence": 30}, {"trip_id": "14691454", "route_id": "6649", "vehicle_id": "9490", "latitude": 49.26380157470703, "longitude": -123.00306701660156, "timestamp": 1764826502, "current_stop_sequence": 35}, {"trip_id": "14692338", "route_id": "6651", "vehicle_id": "9658", "latitude": 49.271484375, "longitude": -123.0031509399414, "timestamp": 1764826491, "current_stop_sequence": 16}, {"trip_id": "14683702", "route_id": "11201", "vehicle_id": "18301", "latitude": 49.25556564331055, "longitude": -123.23611450195312, "timestamp": 1764826493, "current_stop_sequence": 4}, {"trip_id": "14681889", "route_id": "6627", "vehicle_id": "8130", "latitude": 49.2580680847168, "longitude": -123.20038604736328, "timestamp": 1764826493, "current_stop_sequence": 9}, {"trip_id": "14681846", "route_id": "6627", "vehicle_id": "8125", "latitude": 49.2486686706543, "longitude": -123.09603118896484, "timestamp": 1764826501, "current_stop_sequence": 35}, {"trip_id": "14681867", "route_id": "6627", "vehicle_id": "21015", "latitude": 49.2505989074707, "longitude": -123.03446960449219, "timestamp": 1764826488, "current_stop_sequence": 51}, {"trip_id": "14692481", "route_id": "6651", "vehicle_id": "9717", "latitude": 49.244781494140625, "longitude": -123.00343322753906, "timestamp": 1764826482, "current_stop_sequence": 21}, {"trip_id": "14681922", "route_id": "6627", "vehicle_id": "21009", "latitude": 49.24869918823242, "longitude": -123.09065246582031, "timestamp": 1764826505, "current_stop_sequence": 30}, {"trip_id": "14681920", "route_id": "6627", "vehicle_id": "8128", "latitude": 49.26791763305664, "longitude": -123.24678039550781, "timestamp": 1764826211, "current_stop_sequence": 65}, {"trip_id": "14685035", "route_id": "6636", "vehicle_id": "12019", "latitude": 49.268184661865234, "longitude": -123.24765014648438, "timestamp": 1764826463, "current_stop_sequence": 60}, {"trip_id": "14683282", "route_id": "6631", "vehicle_id": "9640", "latitude": 49.24421691894531, "longitude": -123.04536437988281, "timestamp": 1764826485, "current_stop_sequence": 1}, {"trip_id": "14682295", "route_id": "6628", "vehicle_id": "9713", "latitude": 49.22916793823242, "longitude": -123.03206634521484, "timestamp": 1764826468, "current_stop_sequence": 39}, {"trip_id": "14682907", "route_id": "6630", "vehicle_id": "9656", "latitude": 49.23875045776367, "longitude": -123.03288269042969, "timestamp": 1764826247, "current_stop_sequence": 1}, {"trip_id": "14682613", "route_id": "6629", "vehicle_id": "9724", "latitude": 49.276100158691406, "longitude": -123.0335464477539, "timestamp": 1764826491, "current_stop_sequence": 21}, {"trip_id": "14682978", "route_id": "6630", "vehicle_id": "9778", "latitude": 49.277767181396484, "longitude": -123.02371978759766, "timestamp": 1764826487, "current_stop_sequence": 5}, {"trip_id": "14682640", "route_id": "6629", "vehicle_id": "9774", "latitude": 0.0, "longitude": 0.0, "timestamp": 1764826481, "current_stop_sequence": 19}, {"trip_id": "14682906", "route_id": "6630", "vehicle_id": "9781", "latitude": 49.266448974609375, "longitude": -123.0234146118164, "timestamp": 1764826477, "current_stop_sequence": 23}, {"trip_id": "14733691", "route_id": "37810", "vehicle_id": "18017", "latitude": 49.23809814453125, "longitude": -123.03074645996094, "timestamp": 1764826387, "current_stop_sequence": 1}, {"trip_id": "14733730", "route_id": "37810", "vehicle_id": "18014", "latitude": 49.23786544799805, "longitude": -123.03099822998047, "timestamp": 1764826499, "current_stop_sequence": 1}, {"trip_id": "14680758", "route_id": "6626", "vehicle_id": "9452", "latitude": 49.286582946777344, "longitude": -123.1216812133789, "timestamp": 1764826490, "current_stop_sequence": 1}, {"trip_id": "14696783", "route_id": "6667", "vehicle_id": "14005", "latitude": 49.2802848815918, "longitude": -122.97429656982422, "timestamp": 1764826485, "current_stop_sequence": 13}, {"trip_id": "14734262", "route_id": "37807", "vehicle_id": "22004", "latitude": 49.28033447265625, "longitude": -122.95221710205078, "timestamp": 1764826497, "current_stop_sequence": 14}, {"trip_id": "14741462", "route_id": "6658", "vehicle_id": "19046", "latitude": 49.278533935546875, "longitude": -122.91287994384766, "timestamp": 1764826478, "current_stop_sequence": 1}, {"trip_id": "14693844", "route_id": "6657", "vehicle_id": "25175", "latitude": 49.275665283203125, "longitude": -122.94255065917969, "timestamp": 1764826486, "current_stop_sequence": 6}, {"trip_id": "14696853", "route_id": "6667", "vehicle_id": "16035", "latitude": 49.280418395996094, "longitude": -122.96575164794922, "timestamp": 1764826490, "current_stop_sequence": 43}, {"trip_id": "14733497", "route_id": "37810", "vehicle_id": "19012", "latitude": 49.23588180541992, "longitude": -123.20037078857422, "timestamp": 1764826508, "current_stop_sequence": 3}, {"trip_id": "14684887", "route_id": "6636", "vehicle_id": "12022", "latitude": 49.227115631103516, "longitude": -123.15483093261719, "timestamp": 1764826488, "current_stop_sequence": 20}, {"trip_id": "14684885", "route_id": "6636", "vehicle_id": "16207", "latitude": 49.22483444213867, "longitude": -123.05408477783203, "timestamp": 1764826467, "current_stop_sequence": 48}, {"trip_id": "14682355", "route_id": "6628", "vehicle_id": "9768", "latitude": 49.224098205566406, "longitude": -123.03230285644531, "timestamp": 1764826473, "current_stop_sequence": 8}, {"trip_id": "14685038", "route_id": "6636", "vehicle_id": "12011", "latitude": 49.22476577758789, "longitude": -123.04561614990234, "timestamp": 1764826488, "current_stop_sequence": 15}, {"trip_id": "14685037", "route_id": "6636", "vehicle_id": "16213", "latitude": 49.226165771484375, "longitude": -123.11627960205078, "timestamp": 1764826487, "current_stop_sequence": 33}, {"trip_id": "14685036", "route_id": "6636", "vehicle_id": "16205", "latitude": 49.227081298828125, "longitude": -123.14769744873047, "timestamp": 1764826466, "current_stop_sequence": 41}, {"trip_id": "14685537", "route_id": "6637", "vehicle_id": "18354", "latitude": 49.267398834228516, "longitude": -123.13488006591797, "timestamp": 1764826483, "current_stop_sequence": 16}, {"trip_id": "14693494", "route_id": "6654", "vehicle_id": "9628", "latitude": 49.249916076660156, "longitude": -122.9000473022461, "timestamp": 1764826490, "current_stop_sequence": 2}, {"trip_id": "14676682", "route_id": "6620", "vehicle_id": "2508", "latitude": 49.207298278808594, "longitude": -123.1236801147461, "timestamp": 1764826493, "current_stop_sequence": 35}, {"trip_id": "14687493", "route_id": "6642", "vehicle_id": "23201", "latitude": 49.2094841003418, "longitude": -123.1185302734375, "timestamp": 1764826508, "current_stop_sequence": 3}, {"trip_id": "14676681", "route_id": "6620", "vehicle_id": "2521", "latitude": 49.209999084472656, "longitude": -123.11511993408203, "timestamp": 1764825952, "current_stop_sequence": 36}, {"trip_id": "14687427", "route_id": "6642", "vehicle_id": "23213", "latitude": 49.210968017578125, "longitude": -123.07483673095703, "timestamp": 1764826492, "current_stop_sequence": 13}, {"trip_id": "14687471", "route_id": "6642", "vehicle_id": "23209", "latitude": 49.19818115234375, "longitude": -122.95393371582031, "timestamp": 1764826487, "current_stop_sequence": 39}, {"trip_id": "14688016", "route_id": "6643", "vehicle_id": "18172", "latitude": 49.19976806640625, "longitude": -122.9469985961914, "timestamp": 1764826213, "current_stop_sequence": 33}, {"trip_id": "14743462", "route_id": "6811", "vehicle_id": "24520", "latitude": 49.20841598510742, "longitude": -123.01726531982422, "timestamp": 1764826483, "current_stop_sequence": 1}, {"trip_id": "14687603", "route_id": "6642", "vehicle_id": "23211", "latitude": 49.20798110961914, "longitude": -123.02661895751953, "timestamp": 1764826496, "current_stop_sequence": 15}, {"trip_id": "14687518", "route_id": "6642", "vehicle_id": "25102", "latitude": 49.21220016479492, "longitude": -123.11042022705078, "timestamp": 1764826486, "current_stop_sequence": 32}, {"trip_id": "14718849", "route_id": "6728", "vehicle_id": "25104", "latitude": 49.19984817504883, "longitude": -122.94903564453125, "timestamp": 1764826368, "current_stop_sequence": 1}, {"trip_id": "14691807", "route_id": "6662", "vehicle_id": "16019", "latitude": 49.20313262939453, "longitude": -122.94781494140625, "timestamp": 1764826481, "current_stop_sequence": 5}, {"trip_id": "14689249", "route_id": "6796", "vehicle_id": "24513", "latitude": 49.215248107910156, "longitude": -122.9229965209961, "timestamp": 1764826481, "current_stop_sequence": 24}, {"trip_id": "14689466", "route_id": "6645", "vehicle_id": "25135", "latitude": 49.21183395385742, "longitude": -122.91868591308594, "timestamp": 1764826488, "current_stop_sequence": 16}, {"trip_id": "14688314", "route_id": "46099", "vehicle_id": "24519", "latitude": 49.20108413696289, "longitude": -122.9121322631836, "timestamp": 1764826503, "current_stop_sequence": 8}, {"trip_id": "14689304", "route_id": "6796", "vehicle_id": "25503", "latitude": 49.20111846923828, "longitude": -122.91203308105469, "timestamp": 1764826358, "current_stop_sequence": 24}, {"trip_id": "14718840", "route_id": "6728", "vehicle_id": "9426", "latitude": 49.182132720947266, "longitude": -122.95668029785156, "timestamp": 1764826503, "current_stop_sequence": 6}, {"trip_id": "14690911", "route_id": "32799", "vehicle_id": "9421", "latitude": 49.22785186767578, "longitude": -122.99798583984375, "timestamp": 1764826497, "current_stop_sequence": 4}, {"trip_id": "14690973", "route_id": "32799", "vehicle_id": "9401", "latitude": 49.217384338378906, "longitude": -122.95294952392578, "timestamp": 1764826482, "current_stop_sequence": 3}, {"trip_id": "14688240", "route_id": "46099", "vehicle_id": "25610", "latitude": 49.20615005493164, "longitude": -122.90721893310547, "timestamp": 1764826481, "current_stop_sequence": 4}, {"trip_id": "14689601", "route_id": "6645", "vehicle_id": "9508", "latitude": 49.22536849975586, "longitude": -122.938720703125, "timestamp": 1764826478, "current_stop_sequence": 15}, {"trip_id": "14690972", "route_id": "32799", "vehicle_id": "9430", "latitude": 49.21215057373047, "longitude": -122.95805358886719, "timestamp": 1764826493, "current_stop_sequence": 1}, {"trip_id": "14743500", "route_id": "6811", "vehicle_id": "25624", "latitude": 49.22615051269531, "longitude": -123.00334930419922, "timestamp": 1764826485, "current_stop_sequence": 1}, {"trip_id": "14743557", "route_id": "6817", "vehicle_id": "24521", "latitude": 49.22591781616211, "longitude": -123.00301361083984, "timestamp": 1764826503, "current_stop_sequence": 1}, {"trip_id": "14692025", "route_id": "6650", "vehicle_id": "25131", "latitude": 49.234066009521484, "longitude": -123.01348114013672, "timestamp": 1764826476, "current_stop_sequence": 3}, {"trip_id": "14690126", "route_id": "6646", "vehicle_id": "14039", "latitude": 49.22563171386719, "longitude": -123.00281524658203, "timestamp": 1764825978, "current_stop_sequence": 49}, {"trip_id": "14690379", "route_id": "6647", "vehicle_id": "25151", "latitude": 49.21443176269531, "longitude": -122.9392318725586, "timestamp": 1764826481, "current_stop_sequence": 13}, {"trip_id": "14743556", "route_id": "6817", "vehicle_id": "24605", "latitude": 49.21419906616211, "longitude": -122.95939636230469, "timestamp": 1764826498, "current_stop_sequence": 21}, {"trip_id": "14690709", "route_id": "6648", "vehicle_id": "25139", "latitude": 49.21183395385742, "longitude": -122.95843505859375, "timestamp": 1764826487, "current_stop_sequence": 1}, {"trip_id": "14690659", "route_id": "6648", "vehicle_id": "25140", "latitude": 49.220951080322266, "longitude": -123.00505065917969, "timestamp": 1764826491, "current_stop_sequence": 6}, {"trip_id": "14690100", "route_id": "6646", "vehicle_id": "16045", "latitude": 49.24330139160156, "longitude": -122.97343444824219, "timestamp": 1764826492, "current_stop_sequence": 21}, {"trip_id": "14692339", "route_id": "6651", "vehicle_id": "9750", "latitude": 49.225948333740234, "longitude": -123.00228118896484, "timestamp": 1764826313, "current_stop_sequence": 1}, {"trip_id": "14689498", "route_id": "6645", "vehicle_id": "25124", "latitude": 49.21196746826172, "longitude": -122.95870208740234, "timestamp": 1764826478, "current_stop_sequence": 1}, {"trip_id": "14693056", "route_id": "33292", "vehicle_id": "25169", "latitude": 49.23414993286133, "longitude": -122.95680236816406, "timestamp": 1764826493, "current_stop_sequence": 13}, {"trip_id": "14693239", "route_id": "6652", "vehicle_id": "9649", "latitude": 49.26005172729492, "longitude": -122.927734375, "timestamp": 1764826499, "current_stop_sequence": 32}, {"trip_id": "14693280", "route_id": "6652", "vehicle_id": "9620", "latitude": 49.26831817626953, "longitude": -122.99663543701172, "timestamp": 1764826500, "current_stop_sequence": 30}, {"trip_id": "14692790", "route_id": "6776", "vehicle_id": "25516", "latitude": 49.287418365478516, "longitude": -123.0161361694336, "timestamp": 1764826497, "current_stop_sequence": 8}, {"trip_id": "14693054", "route_id": "33292", "vehicle_id": "25148", "latitude": 49.212215423583984, "longitude": -122.95832061767578, "timestamp": 1764826487, "current_stop_sequence": 1}, {"trip_id": "14695273", "route_id": "6659", "vehicle_id": "18169", "latitude": 49.27539825439453, "longitude": -122.7986831665039, "timestamp": 1764826482, "current_stop_sequence": 1}, {"trip_id": "14696777", "route_id": "6667", "vehicle_id": "18174", "latitude": 49.261234283447266, "longitude": -122.77448272705078, "timestamp": 1764826440, "current_stop_sequence": 55}, {"trip_id": "14698072", "route_id": "30039", "vehicle_id": "21541", "latitude": 49.26088333129883, "longitude": -122.77535247802734, "timestamp": 1764826501, "current_stop_sequence": 20}, {"trip_id": "14696845", "route_id": "6667", "vehicle_id": "18180", "latitude": 49.26089859008789, "longitude": -122.7783203125, "timestamp": 1764826505, "current_stop_sequence": 2}, {"trip_id": "14697857", "route_id": "30038", "vehicle_id": "24533", "latitude": 49.274166107177734, "longitude": -122.791748046875, "timestamp": 1764826506, "current_stop_sequence": 26}, {"trip_id": "14696526", "route_id": "6666", "vehicle_id": "18184", "latitude": 49.27618408203125, "longitude": -122.79969787597656, "timestamp": 1764826498, "current_stop_sequence": 42}, {"trip_id": "14699969", "route_id": "30049", "vehicle_id": "21509", "latitude": 49.27633285522461, "longitude": -122.79768371582031, "timestamp": 1764826486, "current_stop_sequence": 1}, {"trip_id": "14695779", "route_id": "6661", "vehicle_id": "18202", "latitude": 49.27021789550781, "longitude": -122.81473541259766, "timestamp": 1764826508, "current_stop_sequence": 7}, {"trip_id": "14696193", "route_id": "6664", "vehicle_id": "14036", "latitude": 49.26356887817383, "longitude": -122.86446380615234, "timestamp": 1764826479, "current_stop_sequence": 39}, {"trip_id": "14693848", "route_id": "6657", "vehicle_id": "25142", "latitude": 49.229331970214844, "longitude": -122.9683837890625, "timestamp": 1764826492, "current_stop_sequence": 37}, {"trip_id": "14734336", "route_id": "37807", "vehicle_id": "22006", "latitude": 49.27851867675781, "longitude": -122.91275024414062, "timestamp": 1764826383, "current_stop_sequence": 1}, {"trip_id": "14696779", "route_id": "6667", "vehicle_id": "18165", "latitude": 49.27668380737305, "longitude": -122.86021423339844, "timestamp": 1764826491, "current_stop_sequence": 27}, {"trip_id": "14699217", "route_id": "30046", "vehicle_id": "21530", "latitude": 49.27640151977539, "longitude": -122.83000183105469, "timestamp": 1764826505, "current_stop_sequence": 5}, {"trip_id": "14732964", "route_id": "37809", "vehicle_id": "18062", "latitude": 49.274898529052734, "longitude": -122.79913330078125, "timestamp": 1764826500, "current_stop_sequence": 1}, {"trip_id": "14699580", "route_id": "30047", "vehicle_id": "24525", "latitude": 49.2779655456543, "longitude": -122.82038116455078, "timestamp": 1764826505, "current_stop_sequence": 13}, {"trip_id": "14698641", "route_id": "30043", "vehicle_id": "24527", "latitude": 49.277748107910156, "longitude": -122.84663391113281, "timestamp": 1764826463, "current_stop_sequence": 5}, {"trip_id": "14690070", "route_id": "6646", "vehicle_id": "16048", "latitude": 49.248348236083984, "longitude": -122.89302062988281, "timestamp": 1764826092, "current_stop_sequence": 48}, {"trip_id": "14689961", "route_id": "16719", "vehicle_id": "24509", "latitude": 49.24283218383789, "longitude": -122.89275360107422, "timestamp": 1764826476, "current_stop_sequence": 2}, {"trip_id": "14699074", "route_id": "30045", "vehicle_id": "21519", "latitude": 49.290584564208984, "longitude": -122.83098602294922, "timestamp": 1764826487, "current_stop_sequence": 27}, {"trip_id": "14696778", "route_id": "6667", "vehicle_id": "14045", "latitude": 49.284000396728516, "longitude": -122.81723022460938, "timestamp": 1764826476, "current_stop_sequence": 40}, {"trip_id": "14696302", "route_id": "6665", "vehicle_id": "14014", "latitude": 49.238548278808594, "longitude": -122.87934875488281, "timestamp": 1764826492, "current_stop_sequence": 4}, {"trip_id": "14699748", "route_id": "30048", "vehicle_id": "21522", "latitude": 49.275917053222656, "longitude": -122.798583984375, "timestamp": 1764826463, "current_stop_sequence": 1}, {"trip_id": "14675450", "route_id": "6618", "vehicle_id": "2537", "latitude": 49.28141784667969, "longitude": -123.1002197265625, "timestamp": 1764826483, "current_stop_sequence": 38}, {"trip_id": "14697186", "route_id": "6668", "vehicle_id": "21525", "latitude": 49.260318756103516, "longitude": -122.79792022705078, "timestamp": 1764826483, "current_stop_sequence": 3}, {"trip_id": "14696156", "route_id": "6664", "vehicle_id": "18190", "latitude": 49.23786544799805, "longitude": -122.84403228759766, "timestamp": 1764826507, "current_stop_sequence": 39}, {"trip_id": "14695778", "route_id": "6661", "vehicle_id": "14034", "latitude": 49.23233413696289, "longitude": -122.88241577148438, "timestamp": 1764826155, "current_stop_sequence": 36}, {"trip_id": "14697404", "route_id": "30036", "vehicle_id": "21508", "latitude": 49.251731872558594, "longitude": -122.77815246582031, "timestamp": 1764826503, "current_stop_sequence": 4}, {"trip_id": "14700452", "route_id": "22638", "vehicle_id": "14010", "latitude": 49.271732330322266, "longitude": -122.7562026977539, "timestamp": 1764826476, "current_stop_sequence": 21}, {"trip_id": "14695554", "route_id": "6660", "vehicle_id": "16004", "latitude": 49.27565002441406, "longitude": -122.79828643798828, "timestamp": 1764826461, "current_stop_sequence": 1}, {"trip_id": "14699263", "route_id": "30046", "vehicle_id": "21538", "latitude": 49.27583312988281, "longitude": -122.79866790771484, "timestamp": 1764826462, "current_stop_sequence": 1}, {"trip_id": "14700713", "route_id": "30051", "vehicle_id": "24532", "latitude": 49.288516998291016, "longitude": -122.77576446533203, "timestamp": 1764826481, "current_stop_sequence": 9}, {"trip_id": "14700881", "route_id": "30584", "vehicle_id": "16037", "latitude": 49.275699615478516, "longitude": -122.8011474609375, "timestamp": 1764826507, "current_stop_sequence": 1}, {"trip_id": "14700913", "route_id": "30584", "vehicle_id": "14009", "latitude": 49.282318115234375, "longitude": -122.80181884765625, "timestamp": 1764826479, "current_stop_sequence": 19}, {"trip_id": "14732329", "route_id": "38311", "vehicle_id": "19043", "latitude": 49.3084831237793, "longitude": -123.06171417236328, "timestamp": 1764826501, "current_stop_sequence": 8}, {"trip_id": "14741597", "route_id": "39307", "vehicle_id": "9782", "latitude": 49.3122673034668, "longitude": -123.02561950683594, "timestamp": 1764826484, "current_stop_sequence": 3}, {"trip_id": "14701071", "route_id": "16717", "vehicle_id": "9681", "latitude": 49.354698181152344, "longitude": -123.02839660644531, "timestamp": 1764826508, "current_stop_sequence": 42}, {"trip_id": "14702592", "route_id": "6676", "vehicle_id": "9769", "latitude": 49.34843444824219, "longitude": -123.02466583251953, "timestamp": 1764826492, "current_stop_sequence": 1}, {"trip_id": "14701085", "route_id": "16717", "vehicle_id": "9708", "latitude": 49.33778381347656, "longitude": -123.03826904296875, "timestamp": 1764826482, "current_stop_sequence": 12}, {"trip_id": "14701351", "route_id": "6673", "vehicle_id": "9788", "latitude": 49.31560134887695, "longitude": -122.97906494140625, "timestamp": 1764826486, "current_stop_sequence": 10}, {"trip_id": "14701390", "route_id": "6673", "vehicle_id": "9770", "latitude": 49.3114013671875, "longitude": -123.00846862792969, "timestamp": 1764826476, "current_stop_sequence": 22}, {"trip_id": "14741773", "route_id": "6674", "vehicle_id": "9715", "latitude": 49.3079833984375, "longitude": -122.98066711425781, "timestamp": 1764826493, "current_stop_sequence": 10}, {"trip_id": "14701863", "route_id": "6675", "vehicle_id": "25525", "latitude": 49.31813430786133, "longitude": -123.00409698486328, "timestamp": 1764826487, "current_stop_sequence": 6}, {"trip_id": "14703848", "route_id": "6682", "vehicle_id": "9619", "latitude": 49.322017669677734, "longitude": -123.06939697265625, "timestamp": 1764826504, "current_stop_sequence": 23}, {"trip_id": "14702564", "route_id": "6676", "vehicle_id": "9784", "latitude": 49.31060028076172, "longitude": -123.08360290527344, "timestamp": 1764826491, "current_stop_sequence": 1}, {"trip_id": "14703327", "route_id": "6679", "vehicle_id": "9630", "latitude": 49.3223991394043, "longitude": -123.07225036621094, "timestamp": 1764826485, "current_stop_sequence": 18}, {"trip_id": "14703073", "route_id": "6678", "vehicle_id": "9716", "latitude": 49.34524917602539, "longitude": -123.0723648071289, "timestamp": 1764826317, "current_stop_sequence": 28}, {"trip_id": "14703286", "route_id": "6679", "vehicle_id": "9791", "latitude": 49.367733001708984, "longitude": -123.10070037841797, "timestamp": 1764826478, "current_stop_sequence": 1}, {"trip_id": "14703543", "route_id": "6680", "vehicle_id": "9789", "latitude": 49.363433837890625, "longitude": -123.10343170166016, "timestamp": 1764826491, "current_stop_sequence": 4}, {"trip_id": "14704711", "route_id": "6685", "vehicle_id": "9666", "latitude": 49.339500427246094, "longitude": -123.11406707763672, "timestamp": 1764826491, "current_stop_sequence": 19}, {"trip_id": "14702800", "route_id": "6677", "vehicle_id": "9786", "latitude": 49.310482025146484, "longitude": -123.08370208740234, "timestamp": 1764826490, "current_stop_sequence": 1}, {"trip_id": "14703908", "route_id": "6682", "vehicle_id": "9758", "latitude": 49.32211685180664, "longitude": -123.07286834716797, "timestamp": 1764826468, "current_stop_sequence": 13}, {"trip_id": "14704681", "route_id": "6685", "vehicle_id": "9709", "latitude": 49.35628128051758, "longitude": -123.09168243408203, "timestamp": 1764826492, "current_stop_sequence": 26}, {"trip_id": "14703068", "route_id": "6678", "vehicle_id": "9751", "latitude": 49.31121826171875, "longitude": -123.079833984375, "timestamp": 1764826484, "current_stop_sequence": 1}, {"trip_id": "14895589", "route_id": "6692", "vehicle_id": "705", "latitude": 49.328582763671875, "longitude": -123.15995025634766, "timestamp": 1764826492, "current_stop_sequence": 8}, {"trip_id": "14895414", "route_id": "6687", "vehicle_id": "1201", "latitude": 49.328582763671875, "longitude": -123.15969848632812, "timestamp": 1764826471, "current_stop_sequence": 45}, {"trip_id": "14706545", "route_id": "6693", "vehicle_id": "16225", "latitude": 49.326900482177734, "longitude": -123.13838195800781, "timestamp": 1764826493, "current_stop_sequence": 3}, {"trip_id": "14895639", "route_id": "6692", "vehicle_id": "1204", "latitude": 49.32701873779297, "longitude": -123.14790344238281, "timestamp": 1764826472, "current_stop_sequence": 43}, {"trip_id": "14895537", "route_id": "6687", "vehicle_id": "1211", "latitude": 49.33808135986328, "longitude": -123.19529724121094, "timestamp": 1764826484, "current_stop_sequence": 26}, {"trip_id": "14895536", "route_id": "6687", "vehicle_id": "906", "latitude": 49.369667053222656, "longitude": -123.27618408203125, "timestamp": 1764826502, "current_stop_sequence": 55}, {"trip_id": "14895981", "route_id": "6689", "vehicle_id": "24503", "latitude": 49.33124923706055, "longitude": -123.16021728515625, "timestamp": 1764826487, "current_stop_sequence": 8}, {"trip_id": "14740298", "route_id": "6748", "vehicle_id": "9584", "latitude": 49.11146545410156, "longitude": -123.05208587646484, "timestamp": 1764826478, "current_stop_sequence": 38}, {"trip_id": "14740212", "route_id": "6748", "vehicle_id": "9425", "latitude": 49.1475830078125, "longitude": -122.94335174560547, "timestamp": 1764826506, "current_stop_sequence": 23}, {"trip_id": "14708215", "route_id": "6702", "vehicle_id": "18386", "latitude": 49.137081146240234, "longitude": -122.8890151977539, "timestamp": 1764826476, "current_stop_sequence": 36}, {"trip_id": "14714979", "route_id": "11692", "vehicle_id": "24135", "latitude": 49.13593292236328, "longitude": -122.89019775390625, "timestamp": 1764826275, "current_stop_sequence": 48}, {"trip_id": "14713928", "route_id": "6715", "vehicle_id": "19407", "latitude": 49.08940124511719, "longitude": -122.9621353149414, "timestamp": 1764826486, "current_stop_sequence": 2}, {"trip_id": "14712684", "route_id": "6713", "vehicle_id": "19413", "latitude": 49.13763427734375, "longitude": -122.88815307617188, "timestamp": 1764826155, "current_stop_sequence": 1}, {"trip_id": "14707822", "route_id": "6700", "vehicle_id": "16111", "latitude": 49.14931869506836, "longitude": -122.91246795654297, "timestamp": 1764826488, "current_stop_sequence": 13}, {"trip_id": "14708064", "route_id": "6701", "vehicle_id": "18360", "latitude": 49.17705154418945, "longitude": -122.88943481445312, "timestamp": 1764826505, "current_stop_sequence": 1}, {"trip_id": "14734900", "route_id": "46604", "vehicle_id": "18061", "latitude": 49.203548431396484, "longitude": -122.87660217285156, "timestamp": 1764826077, "current_stop_sequence": 12}, {"trip_id": "14707893", "route_id": "6700", "vehicle_id": "18362", "latitude": 49.13410186767578, "longitude": -122.89061737060547, "timestamp": 1764826496, "current_stop_sequence": 29}, {"trip_id": "14708437", "route_id": "6703", "vehicle_id": "24126", "latitude": 49.16976547241211, "longitude": -122.89016723632812, "timestamp": 1764826508, "current_stop_sequence": 22}, {"trip_id": "14731923", "route_id": "37808", "vehicle_id": "18026", "latitude": 49.17483139038086, "longitude": -122.84593200683594, "timestamp": 1764826488, "current_stop_sequence": 9}, {"trip_id": "14709356", "route_id": "6705", "vehicle_id": "18105", "latitude": 49.18036651611328, "longitude": -122.84536743164062, "timestamp": 1764826495, "current_stop_sequence": 53}, {"trip_id": "14731799", "route_id": "37808", "vehicle_id": "18063", "latitude": 49.18009948730469, "longitude": -122.84541320800781, "timestamp": 1764826473, "current_stop_sequence": 5}, {"trip_id": "14720233", "route_id": "6738", "vehicle_id": "9705", "latitude": 49.188751220703125, "longitude": -122.84918212890625, "timestamp": 1764826481, "current_stop_sequence": 1}, {"trip_id": "14740300", "route_id": "6748", "vehicle_id": "9424", "latitude": 49.20461654663086, "longitude": -122.87460327148438, "timestamp": 1764826492, "current_stop_sequence": 1}, {"trip_id": "14715681", "route_id": "6819", "vehicle_id": "24608", "latitude": 49.19865036010742, "longitude": -122.81192016601562, "timestamp": 1764826501, "current_stop_sequence": 37}, {"trip_id": "14712158", "route_id": "17707", "vehicle_id": "18110", "latitude": 49.19026565551758, "longitude": -122.84777069091797, "timestamp": 1764826277, "current_stop_sequence": 17}, {"trip_id": "14712172", "route_id": "17707", "vehicle_id": "7502", "latitude": 49.19160079956055, "longitude": -122.80438232421875, "timestamp": 1764826504, "current_stop_sequence": 17}, {"trip_id": "14712517", "route_id": "48855", "vehicle_id": "24603", "latitude": 49.191566467285156, "longitude": -122.80453491210938, "timestamp": 1764826497, "current_stop_sequence": 16}, {"trip_id": "14731924", "route_id": "37808", "vehicle_id": "18041", "latitude": 49.191566467285156, "longitude": -122.80448150634766, "timestamp": 1764826472, "current_stop_sequence": 1}, {"trip_id": "14711776", "route_id": "6712", "vehicle_id": "24140", "latitude": 49.19879913330078, "longitude": -122.80926513671875, "timestamp": 1764826486, "current_stop_sequence": 38}, {"trip_id": "14722929", "route_id": "11696", "vehicle_id": "23602", "latitude": 49.087501525878906, "longitude": -123.06217956542969, "timestamp": 1764825990, "current_stop_sequence": 1}, {"trip_id": "14740213", "route_id": "6748", "vehicle_id": "9444", "latitude": 49.090118408203125, "longitude": -123.05738067626953, "timestamp": 1764826485, "current_stop_sequence": 2}, {"trip_id": "14708514", "route_id": "6703", "vehicle_id": "24119", "latitude": 49.20406723022461, "longitude": -122.87515258789062, "timestamp": 1764826430, "current_stop_sequence": 1}, {"trip_id": "14708513", "route_id": "6703", "vehicle_id": "16104", "latitude": 49.170867919921875, "longitude": -122.89036560058594, "timestamp": 1764826505, "current_stop_sequence": 7}, {"trip_id": "14735030", "route_id": "46604", "vehicle_id": "19002", "latitude": 49.15253448486328, "longitude": -122.89044952392578, "timestamp": 1764826508, "current_stop_sequence": 6}, {"trip_id": "14720011", "route_id": "6737", "vehicle_id": "18132", "latitude": 49.18881607055664, "longitude": -122.84851837158203, "timestamp": 1764826469, "current_stop_sequence": 1}, {"trip_id": "14731798", "route_id": "37808", "vehicle_id": "19001", "latitude": 49.19139862060547, "longitude": -122.80533599853516, "timestamp": 1764826502, "current_stop_sequence": 11}, {"trip_id": "14708885", "route_id": "6704", "vehicle_id": "18367", "latitude": 49.1713981628418, "longitude": -122.80133056640625, "timestamp": 1764826505, "current_stop_sequence": 21}, {"trip_id": "14720325", "route_id": "6738", "vehicle_id": "18116", "latitude": 49.164451599121094, "longitude": -122.79733276367188, "timestamp": 1764826505, "current_stop_sequence": 22}, {"trip_id": "14720234", "route_id": "6738", "vehicle_id": "18363", "latitude": 49.161216735839844, "longitude": -122.78910064697266, "timestamp": 1764826508, "current_stop_sequence": 11}, {"trip_id": "14720780", "route_id": "23384", "vehicle_id": "24101", "latitude": 49.15766525268555, "longitude": -122.7798843383789, "timestamp": 1764826495, "current_stop_sequence": 6}, {"trip_id": "14713136", "route_id": "29038", "vehicle_id": "19125", "latitude": 49.104068756103516, "longitude": -122.73003387451172, "timestamp": 1764826485, "current_stop_sequence": 26}, {"trip_id": "14708923", "route_id": "6704", "vehicle_id": "19120", "latitude": 49.11138153076172, "longitude": -122.7132797241211, "timestamp": 1764826475, "current_stop_sequence": 47}, {"trip_id": "14720875", "route_id": "23384", "vehicle_id": "19106", "latitude": 49.10493469238281, "longitude": -122.6559829711914, "timestamp": 1764826492, "current_stop_sequence": 34}, {"trip_id": "14713170", "route_id": "29038", "vehicle_id": "19133", "latitude": 49.104217529296875, "longitude": -122.71347045898438, "timestamp": 1764826472, "current_stop_sequence": 14}, {"trip_id": "14709004", "route_id": "6704", "vehicle_id": "18138", "latitude": 49.19160079956055, "longitude": -122.81888580322266, "timestamp": 1764826494, "current_stop_sequence": 17}, {"trip_id": "14709314", "route_id": "6705", "vehicle_id": "16112", "latitude": 49.035465240478516, "longitude": -122.80110168457031, "timestamp": 1764826496, "current_stop_sequence": 10}, {"trip_id": "14709299", "route_id": "6705", "vehicle_id": "24129", "latitude": 49.11240005493164, "longitude": -122.84083557128906, "timestamp": 1764826492, "current_stop_sequence": 28}, {"trip_id": "14710959", "route_id": "6707", "vehicle_id": "18147", "latitude": 49.13344955444336, "longitude": -122.83865356445312, "timestamp": 1764826498, "current_stop_sequence": 30}, {"trip_id": "14710450", "route_id": "6706", "vehicle_id": "15005", "latitude": 49.13325119018555, "longitude": -122.8420639038086, "timestamp": 1764825938, "current_stop_sequence": 34}, {"trip_id": "14713171", "route_id": "29038", "vehicle_id": "18144", "latitude": 49.13361740112305, "longitude": -122.84103393554688, "timestamp": 1764826085, "current_stop_sequence": 44}, {"trip_id": "14731800", "route_id": "37808", "vehicle_id": "18012", "latitude": 49.13328170776367, "longitude": -122.84230041503906, "timestamp": 1764826327, "current_stop_sequence": 1}, {"trip_id": "14709462", "route_id": "6705", "vehicle_id": "18152", "latitude": 49.13361740112305, "longitude": -122.84561920166016, "timestamp": 1764826497, "current_stop_sequence": 19}, {"trip_id": "14708511", "route_id": "6703", "vehicle_id": "16120", "latitude": 49.13349914550781, "longitude": -122.84356689453125, "timestamp": 1764826320, "current_stop_sequence": 27}, {"trip_id": "14709946", "route_id": "6821", "vehicle_id": "24604", "latitude": 49.1330680847168, "longitude": -122.84286499023438, "timestamp": 1764826496, "current_stop_sequence": 36}, {"trip_id": "14709414", "route_id": "6705", "vehicle_id": "24143", "latitude": 49.10115051269531, "longitude": -122.82123565673828, "timestamp": 1764826484, "current_stop_sequence": 32}, {"trip_id": "14709508", "route_id": "6705", "vehicle_id": "24148", "latitude": 49.073516845703125, "longitude": -122.82315063476562, "timestamp": 1764826482, "current_stop_sequence": 35}, {"trip_id": "14713452", "route_id": "6714", "vehicle_id": "24128", "latitude": 49.04574966430664, "longitude": -122.80130004882812, "timestamp": 1764826503, "current_stop_sequence": 32}, {"trip_id": "14716003", "route_id": "7321", "vehicle_id": "24107", "latitude": 49.038482666015625, "longitude": -122.80131530761719, "timestamp": 1764826481, "current_stop_sequence": 40}, {"trip_id": "14714503", "route_id": "31818", "vehicle_id": "24601", "latitude": 49.033634185791016, "longitude": -122.80280303955078, "timestamp": 1764826508, "current_stop_sequence": 2}, {"trip_id": "14721283", "route_id": "18705", "vehicle_id": "18115", "latitude": 49.03215026855469, "longitude": -122.80103302001953, "timestamp": 1764826484, "current_stop_sequence": 53}, {"trip_id": "14713927", "route_id": "6715", "vehicle_id": "19415", "latitude": 49.034217834472656, "longitude": -122.80130004882812, "timestamp": 1764826491, "current_stop_sequence": 17}, {"trip_id": "14709419", "route_id": "6705", "vehicle_id": "16110", "latitude": 49.01675033569336, "longitude": -122.7622299194336, "timestamp": 1764826503, "current_stop_sequence": 60}, {"trip_id": "14709947", "route_id": "6821", "vehicle_id": "24618", "latitude": 49.10408401489258, "longitude": -122.89046478271484, "timestamp": 1764826500, "current_stop_sequence": 18}, {"trip_id": "14714943", "route_id": "11692", "vehicle_id": "18148", "latitude": 49.11899948120117, "longitude": -122.86141967773438, "timestamp": 1764826490, "current_stop_sequence": 11}, {"trip_id": "14710904", "route_id": "6707", "vehicle_id": "18159", "latitude": 49.13351821899414, "longitude": -122.85668182373047, "timestamp": 1764826492, "current_stop_sequence": 10}, {"trip_id": "14707362", "route_id": "6698", "vehicle_id": "19424", "latitude": 49.13349914550781, "longitude": -122.84308624267578, "timestamp": 1764826265, "current_stop_sequence": 16}, {"trip_id": "14735028", "route_id": "46604", "vehicle_id": "19020", "latitude": 49.133567810058594, "longitude": -122.85079956054688, "timestamp": 1764826488, "current_stop_sequence": 12}, {"trip_id": "14708438", "route_id": "6703", "vehicle_id": "16128", "latitude": 49.13328170776367, "longitude": -122.8416976928711, "timestamp": 1764826476, "current_stop_sequence": 1}, {"trip_id": "14710026", "route_id": "6821", "vehicle_id": "25614", "latitude": 49.1307487487793, "longitude": -122.85676574707031, "timestamp": 1764826505, "current_stop_sequence": 5}, {"trip_id": "14710025", "route_id": "6821", "vehicle_id": "24633", "latitude": 49.112483978271484, "longitude": -122.86775207519531, "timestamp": 1764826492, "current_stop_sequence": 29}, {"trip_id": "14710342", "route_id": "6706", "vehicle_id": "18158", "latitude": 49.14088439941406, "longitude": -122.84461975097656, "timestamp": 1764826497, "current_stop_sequence": 5}, {"trip_id": "14710325", "route_id": "6706", "vehicle_id": "15021", "latitude": 49.17694854736328, "longitude": -122.867919921875, "timestamp": 1764826506, "current_stop_sequence": 23}, {"trip_id": "14715740", "route_id": "6819", "vehicle_id": "25620", "latitude": 49.19161605834961, "longitude": -122.8566665649414, "timestamp": 1764826488, "current_stop_sequence": 41}, {"trip_id": "14710493", "route_id": "6706", "vehicle_id": "15010", "latitude": 49.18881607055664, "longitude": -122.84931945800781, "timestamp": 1764826320, "current_stop_sequence": 1}, {"trip_id": "14710964", "route_id": "6707", "vehicle_id": "18112", "latitude": 49.19166564941406, "longitude": -122.85618591308594, "timestamp": 1764826485, "current_stop_sequence": 2}, {"trip_id": "14710466", "route_id": "6706", "vehicle_id": "15002", "latitude": 49.19169998168945, "longitude": -122.86173248291016, "timestamp": 1764826485, "current_stop_sequence": 5}, {"trip_id": "14710465", "route_id": "6706", "vehicle_id": "19116", "latitude": 49.133731842041016, "longitude": -122.83879852294922, "timestamp": 1764826497, "current_stop_sequence": 33}, {"trip_id": "14715612", "route_id": "6819", "vehicle_id": "25601", "latitude": 49.18880081176758, "longitude": -122.8488998413086, "timestamp": 1764826508, "current_stop_sequence": 1}, {"trip_id": "14743071", "route_id": "6818", "vehicle_id": "24611", "latitude": 49.188968658447266, "longitude": -122.8494644165039, "timestamp": 1764826499, "current_stop_sequence": 1}, {"trip_id": "14711271", "route_id": "6708", "vehicle_id": "24124", "latitude": 49.147850036621094, "longitude": -122.83474731445312, "timestamp": 1764826508, "current_stop_sequence": 19}, {"trip_id": "14711674", "route_id": "6712", "vehicle_id": "19145", "latitude": 49.13371658325195, "longitude": -122.8358154296875, "timestamp": 1764826503, "current_stop_sequence": 48}, {"trip_id": "14711666", "route_id": "6712", "vehicle_id": "9669", "latitude": 49.19093322753906, "longitude": -122.78983306884766, "timestamp": 1764826481, "current_stop_sequence": 22}, {"trip_id": "14711482", "route_id": "6709", "vehicle_id": "9706", "latitude": 49.165748596191406, "longitude": -122.79015350341797, "timestamp": 1764826485, "current_stop_sequence": 13}, {"trip_id": "14711675", "route_id": "6712", "vehicle_id": "18387", "latitude": 49.18906784057617, "longitude": -122.8490982055664, "timestamp": 1764826500, "current_stop_sequence": 1}, {"trip_id": "14711687", "route_id": "6712", "vehicle_id": "16105", "latitude": 49.18880081176758, "longitude": -122.8483657836914, "timestamp": 1764826507, "current_stop_sequence": 1}, {"trip_id": "14711680", "route_id": "6712", "vehicle_id": "19121", "latitude": 49.19874954223633, "longitude": -122.83441925048828, "timestamp": 1764826468, "current_stop_sequence": 8}, {"trip_id": "14719994", "route_id": "6737", "vehicle_id": "18137", "latitude": 49.19150161743164, "longitude": -122.78421783447266, "timestamp": 1764826506, "current_stop_sequence": 10}, {"trip_id": "14711594", "route_id": "6712", "vehicle_id": "18381", "latitude": 49.1723518371582, "longitude": -122.77888488769531, "timestamp": 1764826500, "current_stop_sequence": 29}, {"trip_id": "14711756", "route_id": "6712", "vehicle_id": "18156", "latitude": 49.18153381347656, "longitude": -122.77863311767578, "timestamp": 1764826488, "current_stop_sequence": 26}, {"trip_id": "14707385", "route_id": "6698", "vehicle_id": "19412", "latitude": 49.15738296508789, "longitude": -122.92581939697266, "timestamp": 1764826403, "current_stop_sequence": 6}, {"trip_id": "14712673", "route_id": "6713", "vehicle_id": "19414", "latitude": 49.1369514465332, "longitude": -122.93138122558594, "timestamp": 1764826481, "current_stop_sequence": 3}, {"trip_id": "14708512", "route_id": "6703", "vehicle_id": "7490", "latitude": 49.1351318359375, "longitude": -122.88465118408203, "timestamp": 1764826508, "current_stop_sequence": 18}, {"trip_id": "14712901", "route_id": "8290", "vehicle_id": "24109", "latitude": 49.16685104370117, "longitude": -122.81231689453125, "timestamp": 1764826486, "current_stop_sequence": 18}, {"trip_id": "14713135", "route_id": "29038", "vehicle_id": "18151", "latitude": 49.13068389892578, "longitude": -122.8233642578125, "timestamp": 1764826508, "current_stop_sequence": 5}, {"trip_id": "14712946", "route_id": "8290", "vehicle_id": "18111", "latitude": 49.184165954589844, "longitude": -122.81178283691406, "timestamp": 1764826480, "current_stop_sequence": 8}, {"trip_id": "14711777", "route_id": "6712", "vehicle_id": "9675", "latitude": 49.1341667175293, "longitude": -122.80097961425781, "timestamp": 1764826501, "current_stop_sequence": 9}, {"trip_id": "14711593", "route_id": "6712", "vehicle_id": "25103", "latitude": 49.143550872802734, "longitude": -122.80123138427734, "timestamp": 1764826488, "current_stop_sequence": 40}, {"trip_id": "14713451", "route_id": "6714", "vehicle_id": "19146", "latitude": 49.14681625366211, "longitude": -122.80126953125, "timestamp": 1764826481, "current_stop_sequence": 11}, {"trip_id": "14713541", "route_id": "40855", "vehicle_id": "18469", "latitude": 49.03118133544922, "longitude": -122.83616638183594, "timestamp": 1764826496, "current_stop_sequence": 20}, {"trip_id": "14713926", "route_id": "6715", "vehicle_id": "19420", "latitude": 49.030601501464844, "longitude": -122.81221771240234, "timestamp": 1764826351, "current_stop_sequence": 21}, {"trip_id": "14713594", "route_id": "40855", "vehicle_id": "9428", "latitude": 49.03126525878906, "longitude": -122.83516693115234, "timestamp": 1764826503, "current_stop_sequence": 11}, {"trip_id": "14709948", "route_id": "6821", "vehicle_id": "24631", "latitude": 49.137367248535156, "longitude": -122.88819885253906, "timestamp": 1764826112, "current_stop_sequence": 1}, {"trip_id": "14720781", "route_id": "23384", "vehicle_id": "24136", "latitude": 49.16976547241211, "longitude": -122.8111343383789, "timestamp": 1764826503, "current_stop_sequence": 4}, {"trip_id": "14714944", "route_id": "11692", "vehicle_id": "24106", "latitude": 49.118934631347656, "longitude": -122.66867065429688, "timestamp": 1764826507, "current_stop_sequence": 41}, {"trip_id": "14720872", "route_id": "23384", "vehicle_id": "18157", "latitude": 49.168216705322266, "longitude": -122.8070297241211, "timestamp": 1764826482, "current_stop_sequence": 45}, {"trip_id": "14737412", "route_id": "6722", "vehicle_id": "9463", "latitude": 49.16353225708008, "longitude": -123.18111419677734, "timestamp": 1764826508, "current_stop_sequence": 16}, {"trip_id": "14738841", "route_id": "6727", "vehicle_id": "9405", "latitude": 49.195533752441406, "longitude": -123.1252670288086, "timestamp": 1764826490, "current_stop_sequence": 45}, {"trip_id": "14737489", "route_id": "6722", "vehicle_id": "9589", "latitude": 49.17020034790039, "longitude": -123.1650161743164, "timestamp": 1764826481, "current_stop_sequence": 8}, {"trip_id": "14737604", "route_id": "6723", "vehicle_id": "9475", "latitude": 49.13378143310547, "longitude": -123.18543243408203, "timestamp": 1764826492, "current_stop_sequence": 34}, {"trip_id": "14737840", "route_id": "6725", "vehicle_id": "9590", "latitude": 49.16263198852539, "longitude": -123.13603210449219, "timestamp": 1764826487, "current_stop_sequence": 3}, {"trip_id": "14718839", "route_id": "6728", "vehicle_id": "25164", "latitude": 49.16998291015625, "longitude": -123.13668060302734, "timestamp": 1764826486, "current_stop_sequence": 35}, {"trip_id": "14716912", "route_id": "6724", "vehicle_id": "9559", "latitude": 49.13346862792969, "longitude": -123.09323120117188, "timestamp": 1764826470, "current_stop_sequence": 5}, {"trip_id": "14716974", "route_id": "6724", "vehicle_id": "9532", "latitude": 49.1378173828125, "longitude": -123.13671875, "timestamp": 1764826470, "current_stop_sequence": 26}, {"trip_id": "14737839", "route_id": "6725", "vehicle_id": "9557", "latitude": 49.134315490722656, "longitude": -123.0655517578125, "timestamp": 1764826468, "current_stop_sequence": 28}, {"trip_id": "14737878", "route_id": "6725", "vehicle_id": "9505", "latitude": 49.159000396728516, "longitude": -123.114013671875, "timestamp": 1764826467, "current_stop_sequence": 19}, {"trip_id": "14737953", "route_id": "34542", "vehicle_id": "9470", "latitude": 49.12693405151367, "longitude": -123.19176483154297, "timestamp": 1764826506, "current_stop_sequence": 2}, {"trip_id": "14737952", "route_id": "34542", "vehicle_id": "9702", "latitude": 49.16266632080078, "longitude": -123.1607666015625, "timestamp": 1764826484, "current_stop_sequence": 27}, {"trip_id": "14738040", "route_id": "34542", "vehicle_id": "9701", "latitude": 49.141082763671875, "longitude": -123.18121337890625, "timestamp": 1764826497, "current_stop_sequence": 22}, {"trip_id": "14738906", "route_id": "6727", "vehicle_id": "9562", "latitude": 49.133567810058594, "longitude": -123.15298461914062, "timestamp": 1764826493, "current_stop_sequence": 44}, {"trip_id": "14739130", "route_id": "34543", "vehicle_id": "9502", "latitude": 49.14076614379883, "longitude": -123.1090316772461, "timestamp": 1764826466, "current_stop_sequence": 13}, {"trip_id": "14718785", "route_id": "6728", "vehicle_id": "25154", "latitude": 49.184532165527344, "longitude": -123.1041488647461, "timestamp": 1764826491, "current_stop_sequence": 16}, {"trip_id": "14738961", "route_id": "6726", "vehicle_id": "9565", "latitude": 49.18450164794922, "longitude": -123.08526611328125, "timestamp": 1764826484, "current_stop_sequence": 17}, {"trip_id": "14718784", "route_id": "6728", "vehicle_id": "25168", "latitude": 49.168365478515625, "longitude": -122.97570037841797, "timestamp": 1764826481, "current_stop_sequence": 25}, {"trip_id": "14718858", "route_id": "6728", "vehicle_id": "9443", "latitude": 49.184600830078125, "longitude": -123.08733367919922, "timestamp": 1764826480, "current_stop_sequence": 19}, {"trip_id": "14738964", "route_id": "6726", "vehicle_id": "9504", "latitude": 49.21080017089844, "longitude": -123.07553100585938, "timestamp": 1764825986, "current_stop_sequence": 1}, {"trip_id": "14738907", "route_id": "6727", "vehicle_id": "9555", "latitude": 49.19206619262695, "longitude": -123.10213470458984, "timestamp": 1764826469, "current_stop_sequence": 8}, {"trip_id": "14742124", "route_id": "12940", "vehicle_id": "16130", "latitude": 49.10749816894531, "longitude": -122.65705108642578, "timestamp": 1764826312, "current_stop_sequence": 20}, {"trip_id": "14719938", "route_id": "6737", "vehicle_id": "18376", "latitude": 49.105098724365234, "longitude": -122.65795135498047, "timestamp": 1764826507, "current_stop_sequence": 1}, {"trip_id": "14720305", "route_id": "6738", "vehicle_id": "18160", "latitude": 49.10751724243164, "longitude": -122.66549682617188, "timestamp": 1764826496, "current_stop_sequence": 4}, {"trip_id": "14720012", "route_id": "6737", "vehicle_id": "18103", "latitude": 49.12215042114258, "longitude": -122.66864776611328, "timestamp": 1764826505, "current_stop_sequence": 33}, {"trip_id": "14720794", "route_id": "23384", "vehicle_id": "18374", "latitude": 49.10798263549805, "longitude": -122.6668472290039, "timestamp": 1764826504, "current_stop_sequence": 14}, {"trip_id": "14720280", "route_id": "6738", "vehicle_id": "19135", "latitude": 49.1143684387207, "longitude": -122.68106842041016, "timestamp": 1764826493, "current_stop_sequence": 26}, {"trip_id": "14720778", "route_id": "23384", "vehicle_id": "24122", "latitude": 49.081565856933594, "longitude": -122.57975006103516, "timestamp": 1764826481, "current_stop_sequence": 27}, {"trip_id": "14720877", "route_id": "23384", "vehicle_id": "18126", "latitude": 49.055599212646484, "longitude": -122.48224639892578, "timestamp": 1764826505, "current_stop_sequence": 13}, {"trip_id": "14722514", "route_id": "6741", "vehicle_id": "18465", "latitude": 49.00638198852539, "longitude": -123.0777816772461, "timestamp": 1764826480, "current_stop_sequence": 1}, {"trip_id": "14723348", "route_id": "6844", "vehicle_id": "25520", "latitude": 49.02735137939453, "longitude": -123.06856536865234, "timestamp": 1764826491, "current_stop_sequence": 11}, {"trip_id": "14722513", "route_id": "6741", "vehicle_id": "18453", "latitude": 49.0901985168457, "longitude": -123.07063293457031, "timestamp": 1764826507, "current_stop_sequence": 35}, {"trip_id": "14722571", "route_id": "6741", "vehicle_id": "9282", "latitude": 49.06516647338867, "longitude": -123.07701873779297, "timestamp": 1764826499, "current_stop_sequence": 20}, {"trip_id": "14707861", "route_id": "6700", "vehicle_id": "19139", "latitude": 49.20313262939453, "longitude": -122.87823486328125, "timestamp": 1764826483, "current_stop_sequence": 1}, {"trip_id": "14724032", "route_id": "6749", "vehicle_id": "16026", "latitude": 49.22050094604492, "longitude": -122.6385498046875, "timestamp": 1764826490, "current_stop_sequence": 25}, {"trip_id": "14725283", "route_id": "34043", "vehicle_id": "21510", "latitude": 49.2193489074707, "longitude": -122.59721374511719, "timestamp": 1764826500, "current_stop_sequence": 20}, {"trip_id": "14724115", "route_id": "6749", "vehicle_id": "16007", "latitude": 49.22060012817383, "longitude": -122.61309814453125, "timestamp": 1764826487, "current_stop_sequence": 5}, {"trip_id": "14742125", "route_id": "12940", "vehicle_id": "18121", "latitude": 49.21786880493164, "longitude": -122.66583251953125, "timestamp": 1764826496, "current_stop_sequence": 1}, {"trip_id": "14725057", "route_id": "6800", "vehicle_id": "21503", "latitude": 49.22773361206055, "longitude": -122.60363006591797, "timestamp": 1764826508, "current_stop_sequence": 27}, {"trip_id": "14724031", "route_id": "6749", "vehicle_id": "14002", "latitude": 49.17304992675781, "longitude": -122.50736999511719, "timestamp": 1764826481, "current_stop_sequence": 1}, {"trip_id": "14696765", "route_id": "6667", "vehicle_id": "18178", "latitude": 49.281532287597656, "longitude": -123.0261001586914, "timestamp": 1764826444, "current_stop_sequence": 1}, {"trip_id": "14741836", "route_id": "6747", "vehicle_id": "21423", "latitude": 49.194583892822266, "longitude": -123.12476348876953, "timestamp": 1764826309, "current_stop_sequence": 5}, {"trip_id": "14741837", "route_id": "6747", "vehicle_id": "19406", "latitude": 49.14699935913086, "longitude": -123.08658599853516, "timestamp": 1764826501, "current_stop_sequence": 5}, {"trip_id": "14685538", "route_id": "6637", "vehicle_id": "18331", "latitude": 49.28023147583008, "longitude": -123.10240173339844, "timestamp": 1764826507, "current_stop_sequence": 1}, {"trip_id": "14737553", "route_id": "6723", "vehicle_id": "9542", "latitude": 49.16761779785156, "longitude": -123.13641357421875, "timestamp": 1764826440, "current_stop_sequence": 30}, {"trip_id": "14695482", "route_id": "6660", "vehicle_id": "14001", "latitude": 49.251834869384766, "longitude": -122.81559753417969, "timestamp": 1764826491, "current_stop_sequence": 30}, {"trip_id": "14733052", "route_id": "37809", "vehicle_id": "18042", "latitude": 49.25849914550781, "longitude": -122.75444793701172, "timestamp": 1764826467, "current_stop_sequence": 5}, {"trip_id": "14895956", "route_id": "6689", "vehicle_id": "25524", "latitude": 49.33676528930664, "longitude": -123.15028381347656, "timestamp": 1764826465, "current_stop_sequence": 12}, {"trip_id": "14686234", "route_id": "6638", "vehicle_id": "8127", "latitude": 49.26905059814453, "longitude": -123.21862030029297, "timestamp": 1764826496, "current_stop_sequence": 3}, {"trip_id": "14695710", "route_id": "6661", "vehicle_id": "14026", "latitude": 49.23301696777344, "longitude": -122.88316345214844, "timestamp": 1764826469, "current_stop_sequence": 1}, {"trip_id": "14691828", "route_id": "6662", "vehicle_id": "14015", "latitude": 49.233184814453125, "longitude": -122.88324737548828, "timestamp": 1764826476, "current_stop_sequence": 1}, {"trip_id": "14697151", "route_id": "6668", "vehicle_id": "21540", "latitude": 49.235565185546875, "longitude": -122.86710357666016, "timestamp": 1764826497, "current_stop_sequence": 4}, {"trip_id": "14680238", "route_id": "6625", "vehicle_id": "2511", "latitude": 49.26948165893555, "longitude": -123.069580078125, "timestamp": 1764826493, "current_stop_sequence": 26}, {"trip_id": "14686856", "route_id": "6641", "vehicle_id": "22001", "latitude": 49.262550354003906, "longitude": -123.09465026855469, "timestamp": 1764826505, "current_stop_sequence": 1}, {"trip_id": "14706610", "route_id": "6693", "vehicle_id": "24016", "latitude": 49.3474006652832, "longitude": -123.19306945800781, "timestamp": 1764826485, "current_stop_sequence": 7}, {"trip_id": "14895714", "route_id": "6691", "vehicle_id": "1614", "latitude": 49.346099853515625, "longitude": -123.14248657226562, "timestamp": 1764826492, "current_stop_sequence": 9}, {"trip_id": "14721482", "route_id": "20667", "vehicle_id": "19404", "latitude": 49.24774932861328, "longitude": -122.8949203491211, "timestamp": 1764826157, "current_stop_sequence": 1}, {"trip_id": "14693756", "route_id": "6657", "vehicle_id": "9431", "latitude": 49.26169967651367, "longitude": -122.96797943115234, "timestamp": 1764826487, "current_stop_sequence": 26}, {"trip_id": "14690143", "route_id": "6646", "vehicle_id": "16017", "latitude": 49.258766174316406, "longitude": -122.96389770507812, "timestamp": 1764826508, "current_stop_sequence": 23}, {"trip_id": "14698593", "route_id": "30043", "vehicle_id": "24508", "latitude": 49.247615814208984, "longitude": -122.89471435546875, "timestamp": 1764826463, "current_stop_sequence": 1}, {"trip_id": "14692993", "route_id": "33292", "vehicle_id": "25119", "latitude": 49.26446533203125, "longitude": -122.98128509521484, "timestamp": 1764826471, "current_stop_sequence": 1}, {"trip_id": "14692107", "route_id": "6650", "vehicle_id": "25112", "latitude": 49.2644157409668, "longitude": -123.01436614990234, "timestamp": 1764826476, "current_stop_sequence": 23}, {"trip_id": "14734352", "route_id": "37807", "vehicle_id": "23013", "latitude": 49.28044891357422, "longitude": -122.9704818725586, "timestamp": 1764826500, "current_stop_sequence": 3}, {"trip_id": "14693477", "route_id": "6654", "vehicle_id": "9732", "latitude": 49.26993179321289, "longitude": -122.94093322753906, "timestamp": 1764826477, "current_stop_sequence": 18}, {"trip_id": "14714724", "route_id": "31819", "vehicle_id": "24634", "latitude": 49.023765563964844, "longitude": -122.79859924316406, "timestamp": 1764826501, "current_stop_sequence": 7}, {"trip_id": "14686563", "route_id": "6641", "vehicle_id": "19018", "latitude": 49.26333236694336, "longitude": -123.06884765625, "timestamp": 1764826497, "current_stop_sequence": 13}, {"trip_id": "14708922", "route_id": "6704", "vehicle_id": "19112", "latitude": 49.16291809082031, "longitude": -122.79444885253906, "timestamp": 1764825967, "current_stop_sequence": 24}, {"trip_id": "14689107", "route_id": "6644", "vehicle_id": "25138", "latitude": 49.16775131225586, "longitude": -122.96178436279297, "timestamp": 1764826493, "current_stop_sequence": 19}, {"trip_id": "14703846", "route_id": "6682", "vehicle_id": "9756", "latitude": 49.290748596191406, "longitude": -123.13065338134766, "timestamp": 1764826480, "current_stop_sequence": 5}, {"trip_id": "14675455", "route_id": "6618", "vehicle_id": "2530", "latitude": 49.21113204956055, "longitude": -123.09288024902344, "timestamp": 1764826393, "current_stop_sequence": 1}, {"trip_id": "14700278", "route_id": "30050", "vehicle_id": "24539", "latitude": 49.3032341003418, "longitude": -122.80656433105469, "timestamp": 1764826478, "current_stop_sequence": 6}, {"trip_id": "14699262", "route_id": "30046", "vehicle_id": "21521", "latitude": 49.29801559448242, "longitude": -122.8346176147461, "timestamp": 1764826484, "current_stop_sequence": 27}, {"trip_id": "14698019", "route_id": "30039", "vehicle_id": "21507", "latitude": 49.26536560058594, "longitude": -122.77314758300781, "timestamp": 1764826492, "current_stop_sequence": 16}, {"trip_id": "14676489", "route_id": "6620", "vehicle_id": "2533", "latitude": 49.21424865722656, "longitude": -123.1402359008789, "timestamp": 1764826389, "current_stop_sequence": 11}, {"trip_id": "14719926", "route_id": "6737", "vehicle_id": "18143", "latitude": 49.163700103759766, "longitude": -122.65979766845703, "timestamp": 1764826499, "current_stop_sequence": 24}, {"trip_id": "14725188", "route_id": "34042", "vehicle_id": "21551", "latitude": 49.189483642578125, "longitude": -122.54035186767578, "timestamp": 1764826495, "current_stop_sequence": 1}, {"trip_id": "14707449", "route_id": "6698", "vehicle_id": "19428", "latitude": 49.15796661376953, "longitude": -122.92645263671875, "timestamp": 1764826494, "current_stop_sequence": 12}, {"trip_id": "14741461", "route_id": "6658", "vehicle_id": "19032", "latitude": 49.25320053100586, "longitude": -122.91753387451172, "timestamp": 1764826500, "current_stop_sequence": 7}, {"trip_id": "14742722", "route_id": "7224", "vehicle_id": "16023", "latitude": 49.24026870727539, "longitude": -122.76306915283203, "timestamp": 1764826484, "current_stop_sequence": 33}, {"trip_id": "14709003", "route_id": "6704", "vehicle_id": "16116", "latitude": 49.1077995300293, "longitude": -122.73111724853516, "timestamp": 1764826508, "current_stop_sequence": 21}, {"trip_id": "14724617", "route_id": "34541", "vehicle_id": "21547", "latitude": 49.221168518066406, "longitude": -122.67259979248047, "timestamp": 1764826463, "current_stop_sequence": 1}, {"trip_id": "14743665", "route_id": "6806", "vehicle_id": "25504", "latitude": 49.21485137939453, "longitude": -122.99378204345703, "timestamp": 1764826471, "current_stop_sequence": 3}, {"trip_id": "14724588", "route_id": "34541", "vehicle_id": "24536", "latitude": 49.225582122802734, "longitude": -122.6857681274414, "timestamp": 1764826488, "current_stop_sequence": 21}, {"trip_id": "14738307", "route_id": "6730", "vehicle_id": "9472", "latitude": 49.222049713134766, "longitude": -123.02243041992188, "timestamp": 1764826508, "current_stop_sequence": 2}, {"trip_id": "14686233", "route_id": "6638", "vehicle_id": "21014", "latitude": 49.26914978027344, "longitude": -123.10401916503906, "timestamp": 1764826483, "current_stop_sequence": 15}, {"trip_id": "14686232", "route_id": "6638", "vehicle_id": "9440", "latitude": 49.26601791381836, "longitude": -123.13054656982422, "timestamp": 1764825977, "current_stop_sequence": 19}, {"trip_id": "14725109", "route_id": "6800", "vehicle_id": "24538", "latitude": 49.217533111572266, "longitude": -122.66694641113281, "timestamp": 1764826501, "current_stop_sequence": 33}, {"trip_id": "14713845", "route_id": "6715", "vehicle_id": "19429", "latitude": 49.06453323364258, "longitude": -122.8169174194336, "timestamp": 1764826490, "current_stop_sequence": 20}, {"trip_id": "14743197", "route_id": "33538", "vehicle_id": "24517", "latitude": 49.2690315246582, "longitude": -123.24749755859375, "timestamp": 1764826508, "current_stop_sequence": 12}, {"trip_id": "14737696", "route_id": "30055", "vehicle_id": "18392", "latitude": 49.27406692504883, "longitude": -123.11511993408203, "timestamp": 1764826496, "current_stop_sequence": 8}, {"trip_id": "14740861", "route_id": "6612", "vehicle_id": "21007", "latitude": 49.27263259887695, "longitude": -123.15809631347656, "timestamp": 1764826505, "current_stop_sequence": 21}, {"trip_id": "14736848", "route_id": "6615", "vehicle_id": "2167", "latitude": 49.28023147583008, "longitude": -123.11181640625, "timestamp": 1764826086, "current_stop_sequence": 1}, {"trip_id": "14686784", "route_id": "6641", "vehicle_id": "19009", "latitude": 49.26256561279297, "longitude": -123.09037017822266, "timestamp": 1764826497, "current_stop_sequence": 4}, {"trip_id": "14720358", "route_id": "6738", "vehicle_id": "19136", "latitude": 49.131282806396484, "longitude": -122.71946716308594, "timestamp": 1764826473, "current_stop_sequence": 14}, {"trip_id": "14720779", "route_id": "23384", "vehicle_id": "18379", "latitude": 49.133148193359375, "longitude": -122.72489929199219, "timestamp": 1764826497, "current_stop_sequence": 9}, {"trip_id": "14720874", "route_id": "23384", "vehicle_id": "24131", "latitude": 49.124332427978516, "longitude": -122.7032470703125, "timestamp": 1764826503, "current_stop_sequence": 5}, {"trip_id": "14720873", "route_id": "23384", "vehicle_id": "19132", "latitude": 49.14023208618164, "longitude": -122.73933410644531, "timestamp": 1764826469, "current_stop_sequence": 39}, {"trip_id": "14683763", "route_id": "11201", "vehicle_id": "18325", "latitude": 49.258731842041016, "longitude": -123.23880004882812, "timestamp": 1764826500, "current_stop_sequence": 42}, {"trip_id": "14680720", "route_id": "6626", "vehicle_id": "18404", "latitude": 49.250450134277344, "longitude": -123.0761489868164, "timestamp": 1764826490, "current_stop_sequence": 26}, {"trip_id": "14712691", "route_id": "6713", "vehicle_id": "21410", "latitude": 49.1879997253418, "longitude": -122.947265625, "timestamp": 1764826499, "current_stop_sequence": 12}, {"trip_id": "14718783", "route_id": "6728", "vehicle_id": "25183", "latitude": 49.1997184753418, "longitude": -122.95006561279297, "timestamp": 1764826476, "current_stop_sequence": 36}, {"trip_id": "14677652", "route_id": "6621", "vehicle_id": "18312", "latitude": 49.2103157043457, "longitude": -123.11724853515625, "timestamp": 1764826483, "current_stop_sequence": 22}, {"trip_id": "14709415", "route_id": "6705", "vehicle_id": "18102", "latitude": 49.189815521240234, "longitude": -122.84773254394531, "timestamp": 1764826482, "current_stop_sequence": 1}, {"trip_id": "14709509", "route_id": "6705", "vehicle_id": "16124", "latitude": 49.18971633911133, "longitude": -122.84771728515625, "timestamp": 1764826230, "current_stop_sequence": 1}, {"trip_id": "14702866", "route_id": "6677", "vehicle_id": "9759", "latitude": 49.33653259277344, "longitude": -123.03900146484375, "timestamp": 1764826468, "current_stop_sequence": 1}, {"trip_id": "14703907", "route_id": "6682", "vehicle_id": "9645", "latitude": 49.33660125732422, "longitude": -123.03880310058594, "timestamp": 1764826445, "current_stop_sequence": 1}, {"trip_id": "14733053", "route_id": "37809", "vehicle_id": "18053", "latitude": 49.21711730957031, "longitude": -122.62538146972656, "timestamp": 1764826492, "current_stop_sequence": 1}, {"trip_id": "14735031", "route_id": "46604", "vehicle_id": "18019", "latitude": 49.186317443847656, "longitude": -122.8916015625, "timestamp": 1764826505, "current_stop_sequence": 2}, {"trip_id": "14675026", "route_id": "6617", "vehicle_id": "2264", "latitude": 49.281517028808594, "longitude": -123.09971618652344, "timestamp": 1764826493, "current_stop_sequence": 25}, {"trip_id": "14683764", "route_id": "11201", "vehicle_id": "18389", "latitude": 49.24024963378906, "longitude": -123.08111572265625, "timestamp": 1764826486, "current_stop_sequence": 9}, {"trip_id": "14683701", "route_id": "11201", "vehicle_id": "18315", "latitude": 49.24038314819336, "longitude": -123.09636688232422, "timestamp": 1764826508, "current_stop_sequence": 34}, {"trip_id": "14681845", "route_id": "6627", "vehicle_id": "18335", "latitude": 49.26561737060547, "longitude": -123.00306701660156, "timestamp": 1764826250, "current_stop_sequence": 62}, {"trip_id": "14741729", "route_id": "39307", "vehicle_id": "9605", "latitude": 49.32063293457031, "longitude": -123.01820373535156, "timestamp": 1764826492, "current_stop_sequence": 1}, {"trip_id": "14895640", "route_id": "6692", "vehicle_id": "1607", "latitude": 49.31926727294922, "longitude": -123.01866912841797, "timestamp": 1764826470, "current_stop_sequence": 1}, {"trip_id": "14895641", "route_id": "6692", "vehicle_id": "1610", "latitude": 49.31916809082031, "longitude": -123.01834869384766, "timestamp": 1764826418, "current_stop_sequence": 1}, {"trip_id": "14738039", "route_id": "34542", "vehicle_id": "9585", "latitude": 49.13010025024414, "longitude": -123.18135070800781, "timestamp": 1764826493, "current_stop_sequence": 37}, {"trip_id": "14697828", "route_id": "30038", "vehicle_id": "24535", "latitude": 49.274566650390625, "longitude": -122.79906463623047, "timestamp": 1764826490, "current_stop_sequence": 1}, {"trip_id": "14722572", "route_id": "6741", "vehicle_id": "18467", "latitude": 49.195098876953125, "longitude": -123.12736511230469, "timestamp": 1764826504, "current_stop_sequence": 1}, {"trip_id": "14707355", "route_id": "6698", "vehicle_id": "19431", "latitude": 49.168968200683594, "longitude": -123.13578033447266, "timestamp": 1764826502, "current_stop_sequence": 1}, {"trip_id": "14716957", "route_id": "6724", "vehicle_id": "9665", "latitude": 49.19521713256836, "longitude": -123.12648010253906, "timestamp": 1764826226, "current_stop_sequence": 1}, {"trip_id": "14672663", "route_id": "6613", "vehicle_id": "2512", "latitude": 49.209083557128906, "longitude": -123.11618041992188, "timestamp": 1764826477, "current_stop_sequence": 1}, {"trip_id": "14672664", "route_id": "6613", "vehicle_id": "2515", "latitude": 49.20920181274414, "longitude": -123.115966796875, "timestamp": 1764826485, "current_stop_sequence": 1}, {"trip_id": "14677614", "route_id": "6621", "vehicle_id": "18310", "latitude": 49.20920181274414, "longitude": -123.1162338256836, "timestamp": 1764826485, "current_stop_sequence": 1}, {"trip_id": "14713929", "route_id": "6715", "vehicle_id": "21421", "latitude": 49.194984436035156, "longitude": -123.1268310546875, "timestamp": 1764826508, "current_stop_sequence": 1}, {"trip_id": "14738306", "route_id": "6730", "vehicle_id": "9572", "latitude": 49.19219970703125, "longitude": -123.12448120117188, "timestamp": 1764826481, "current_stop_sequence": 17}, {"trip_id": "14686564", "route_id": "6641", "vehicle_id": "19010", "latitude": 49.26303482055664, "longitude": -123.10706329345703, "timestamp": 1764826508, "current_stop_sequence": 9}, {"trip_id": "14718786", "route_id": "6728", "vehicle_id": "25141", "latitude": 49.163516998291016, "longitude": -123.13616943359375, "timestamp": 1764825961, "current_stop_sequence": 1}, {"trip_id": "14676591", "route_id": "6620", "vehicle_id": "2520", "latitude": 49.2765998840332, "longitude": -123.1269302368164, "timestamp": 1764826481, "current_stop_sequence": 31}, {"trip_id": "14734338", "route_id": "37807", "vehicle_id": "22008", "latitude": 49.28446578979492, "longitude": -123.11750030517578, "timestamp": 1764826504, "current_stop_sequence": 15}, {"trip_id": "14678245", "route_id": "6622", "vehicle_id": "2108", "latitude": 49.27579879760742, "longitude": -123.1283187866211, "timestamp": 1764826500, "current_stop_sequence": 45}, {"trip_id": "14737796", "route_id": "30055", "vehicle_id": "18309", "latitude": 49.277915954589844, "longitude": -123.11051940917969, "timestamp": 1764826499, "current_stop_sequence": 5}, {"trip_id": "14707614", "route_id": "6822", "vehicle_id": "9541", "latitude": 49.082298278808594, "longitude": -123.00885009765625, "timestamp": 1764826476, "current_stop_sequence": 17}, {"trip_id": "14673249", "route_id": "6614", "vehicle_id": "2250", "latitude": 49.2806510925293, "longitude": -123.1211166381836, "timestamp": 1764826507, "current_stop_sequence": 6}, {"trip_id": "14701086", "route_id": "16717", "vehicle_id": "9757", "latitude": 49.280418395996094, "longitude": -123.10116577148438, "timestamp": 1764826481, "current_stop_sequence": 42}, {"trip_id": "14685426", "route_id": "6637", "vehicle_id": "18353", "latitude": 49.28089904785156, "longitude": -123.12055206298828, "timestamp": 1764826508, "current_stop_sequence": 12}, {"trip_id": "14696357", "route_id": "6665", "vehicle_id": "18189", "latitude": 49.238582611083984, "longitude": -122.87909698486328, "timestamp": 1764826496, "current_stop_sequence": 26}, {"trip_id": "14700487", "route_id": "22638", "vehicle_id": "14019", "latitude": 49.26148223876953, "longitude": -122.75599670410156, "timestamp": 1764826493, "current_stop_sequence": 13}, {"trip_id": "14703281", "route_id": "6679", "vehicle_id": "9772", "latitude": 49.30626678466797, "longitude": -123.03616333007812, "timestamp": 1764826476, "current_stop_sequence": 43}, {"trip_id": "14673103", "route_id": "6614", "vehicle_id": "2169", "latitude": 49.28435134887695, "longitude": -123.11521911621094, "timestamp": 1764826506, "current_stop_sequence": 29}, {"trip_id": "14680346", "route_id": "6625", "vehicle_id": "2531", "latitude": 49.28496551513672, "longitude": -123.1143798828125, "timestamp": 1764826477, "current_stop_sequence": 5}, {"trip_id": "14895413", "route_id": "6687", "vehicle_id": "1608", "latitude": 49.325416564941406, "longitude": -123.12966918945312, "timestamp": 1764826472, "current_stop_sequence": 15}, {"trip_id": "14684027", "route_id": "6633", "vehicle_id": "2195", "latitude": 49.23820114135742, "longitude": -123.03105163574219, "timestamp": 1764826498, "current_stop_sequence": 1}, {"trip_id": "14684061", "route_id": "6633", "vehicle_id": "2127", "latitude": 49.23828125, "longitude": -123.03116607666016, "timestamp": 1764826451, "current_stop_sequence": 1}, {"trip_id": "14696604", "route_id": "6666", "vehicle_id": "18204", "latitude": 49.23423385620117, "longitude": -122.86163330078125, "timestamp": 1764826493, "current_stop_sequence": 40}, {"trip_id": "14691455", "route_id": "6649", "vehicle_id": "9509", "latitude": 49.20048141479492, "longitude": -122.91218566894531, "timestamp": 1764826476, "current_stop_sequence": 1}, {"trip_id": "14689597", "route_id": "6645", "vehicle_id": "9495", "latitude": 49.201881408691406, "longitude": -122.9128646850586, "timestamp": 1764826501, "current_stop_sequence": 1}, {"trip_id": "14686566", "route_id": "6641", "vehicle_id": "16221", "latitude": 49.26369857788086, "longitude": -123.14752960205078, "timestamp": 1764826473, "current_stop_sequence": 6}, {"trip_id": "14721324", "route_id": "18705", "vehicle_id": "18142", "latitude": 49.118133544921875, "longitude": -122.67461395263672, "timestamp": 1764826503, "current_stop_sequence": 1}, {"trip_id": "14684888", "route_id": "6636", "vehicle_id": "12010", "latitude": 49.23891830444336, "longitude": -123.21393585205078, "timestamp": 1764826482, "current_stop_sequence": 6}, {"trip_id": "14715969", "route_id": "7321", "vehicle_id": "9674", "latitude": 49.12411880493164, "longitude": -122.8009033203125, "timestamp": 1764826491, "current_stop_sequence": 32}, {"trip_id": "14677030", "route_id": "16718", "vehicle_id": "2289", "latitude": 49.26588439941406, "longitude": -123.24825286865234, "timestamp": 1764826093, "current_stop_sequence": 1}, {"trip_id": "14673138", "route_id": "6614", "vehicle_id": "2267", "latitude": 49.26603317260742, "longitude": -123.24752044677734, "timestamp": 1764825973, "current_stop_sequence": 1}, {"trip_id": "14721529", "route_id": "20667", "vehicle_id": "21418", "latitude": 49.15993118286133, "longitude": -122.66062927246094, "timestamp": 1764826508, "current_stop_sequence": 1}, {"trip_id": "14696844", "route_id": "6667", "vehicle_id": "18201", "latitude": 49.28295135498047, "longitude": -122.8282699584961, "timestamp": 1764826492, "current_stop_sequence": 22}, {"trip_id": "14710434", "route_id": "6706", "vehicle_id": "16126", "latitude": 49.1550178527832, "longitude": -122.86810302734375, "timestamp": 1764826507, "current_stop_sequence": 19}, {"trip_id": "14693229", "route_id": "6652", "vehicle_id": "9637", "latitude": 49.26678466796875, "longitude": -123.00118255615234, "timestamp": 1764826485, "current_stop_sequence": 1}, {"trip_id": "14740299", "route_id": "6748", "vehicle_id": "9515", "latitude": 49.15739822387695, "longitude": -122.93990325927734, "timestamp": 1764826480, "current_stop_sequence": 14}, {"trip_id": "14739050", "route_id": "34543", "vehicle_id": "9581", "latitude": 49.13401794433594, "longitude": -123.09214782714844, "timestamp": 1764826479, "current_stop_sequence": 23}, {"trip_id": "14743146", "route_id": "33538", "vehicle_id": "25523", "latitude": 49.25320053100586, "longitude": -123.24031829833984, "timestamp": 1764826477, "current_stop_sequence": 7}, {"trip_id": "14678933", "route_id": "6623", "vehicle_id": "2208", "latitude": 49.277015686035156, "longitude": -123.11636352539062, "timestamp": 1764826487, "current_stop_sequence": 30}, {"trip_id": "14687418", "route_id": "6642", "vehicle_id": "25202", "latitude": 49.203216552734375, "longitude": -123.13314819335938, "timestamp": 1764826493, "current_stop_sequence": 1}, {"trip_id": "14690710", "route_id": "6648", "vehicle_id": "25110", "latitude": 49.20090103149414, "longitude": -123.01628112792969, "timestamp": 1764826490, "current_stop_sequence": 19}, {"trip_id": "14686667", "route_id": "6641", "vehicle_id": "24014", "latitude": 49.26773452758789, "longitude": -123.24745178222656, "timestamp": 1764826492, "current_stop_sequence": 1}, {"trip_id": "14712095", "route_id": "17707", "vehicle_id": "19114", "latitude": 49.19490051269531, "longitude": -122.7896499633789, "timestamp": 1764826504, "current_stop_sequence": 6}, {"trip_id": "14720322", "route_id": "6738", "vehicle_id": "9688", "latitude": 49.1888313293457, "longitude": -122.8478012084961, "timestamp": 1764826322, "current_stop_sequence": 29}, {"trip_id": "14720870", "route_id": "23384", "vehicle_id": "18106", "latitude": 49.1888313293457, "longitude": -122.84808349609375, "timestamp": 1764825983, "current_stop_sequence": 48}, {"trip_id": "14684884", "route_id": "6636", "vehicle_id": "12013", "latitude": 49.22468185424805, "longitude": -123.03600311279297, "timestamp": 1764826475, "current_stop_sequence": 52}, {"trip_id": "14742090", "route_id": "12940", "vehicle_id": "19143", "latitude": 49.13083267211914, "longitude": -122.64586639404297, "timestamp": 1764826500, "current_stop_sequence": 7}, {"trip_id": "14696347", "route_id": "6665", "vehicle_id": "16013", "latitude": 49.261234283447266, "longitude": -122.88981628417969, "timestamp": 1764825967, "current_stop_sequence": 1}, {"trip_id": "14695259", "route_id": "6659", "vehicle_id": "16031", "latitude": 49.26084899902344, "longitude": -122.89035034179688, "timestamp": 1764826487, "current_stop_sequence": 1}, {"trip_id": "14736972", "route_id": "6616", "vehicle_id": "2221", "latitude": 49.27593231201172, "longitude": -123.12428283691406, "timestamp": 1764826500, "current_stop_sequence": 11}, {"trip_id": "14685950", "route_id": "33538", "vehicle_id": "25511", "latitude": 49.2675666809082, "longitude": -123.24711608886719, "timestamp": 1764826433, "current_stop_sequence": 1}, {"trip_id": "14733535", "route_id": "37810", "vehicle_id": "18030", "latitude": 49.26791763305664, "longitude": -123.24738311767578, "timestamp": 1764826290, "current_stop_sequence": 1}, {"trip_id": "14682309", "route_id": "6628", "vehicle_id": "9664", "latitude": 49.244415283203125, "longitude": -123.0445327758789, "timestamp": 1764826503, "current_stop_sequence": 1}, {"trip_id": "14714764", "route_id": "31819", "vehicle_id": "25619", "latitude": 49.06151580810547, "longitude": -122.80048370361328, "timestamp": 1764826491, "current_stop_sequence": 6}, {"trip_id": "14690974", "route_id": "32799", "vehicle_id": "9446", "latitude": 49.22639846801758, "longitude": -123.00479888916016, "timestamp": 1764826315, "current_stop_sequence": 21}, {"trip_id": "14693791", "route_id": "6657", "vehicle_id": "25182", "latitude": 49.22508239746094, "longitude": -123.0020523071289, "timestamp": 1764826479, "current_stop_sequence": 1}, {"trip_id": "14724858", "route_id": "31822", "vehicle_id": "21557", "latitude": 49.2191162109375, "longitude": -122.59622955322266, "timestamp": 1764825939, "current_stop_sequence": 15}, {"trip_id": "14686781", "route_id": "6641", "vehicle_id": "22009", "latitude": 49.26823425292969, "longitude": -123.248046875, "timestamp": 1764826333, "current_stop_sequence": 14}, {"trip_id": "14678084", "route_id": "6622", "vehicle_id": "2285", "latitude": 49.28181838989258, "longitude": -123.1063003540039, "timestamp": 1764826506, "current_stop_sequence": 39}, {"trip_id": "14679006", "route_id": "6623", "vehicle_id": "2282", "latitude": 49.261600494384766, "longitude": -123.1151351928711, "timestamp": 1764826491, "current_stop_sequence": 12}, {"trip_id": "14683950", "route_id": "6633", "vehicle_id": "2165", "latitude": 49.233367919921875, "longitude": -123.1142807006836, "timestamp": 1764826505, "current_stop_sequence": 23}, {"trip_id": "14703882", "route_id": "6682", "vehicle_id": "9735", "latitude": 49.27958297729492, "longitude": -123.11383056640625, "timestamp": 1764826001, "current_stop_sequence": 39}, {"trip_id": "14895412", "route_id": "6687", "vehicle_id": "704", "latitude": 49.280250549316406, "longitude": -123.11466979980469, "timestamp": 1764826131, "current_stop_sequence": 59}, {"trip_id": "14737797", "route_id": "30055", "vehicle_id": "18338", "latitude": 49.27399826049805, "longitude": -123.09861755371094, "timestamp": 1764826447, "current_stop_sequence": 1}, {"trip_id": "14733690", "route_id": "37810", "vehicle_id": "18005", "latitude": 49.23474884033203, "longitude": -123.16531372070312, "timestamp": 1764826491, "current_stop_sequence": 12}, {"trip_id": "14732963", "route_id": "37809", "vehicle_id": "18056", "latitude": 49.228050231933594, "longitude": -122.68193054199219, "timestamp": 1764826495, "current_stop_sequence": 5}, {"trip_id": "14732962", "route_id": "37809", "vehicle_id": "16043", "latitude": 49.21796798706055, "longitude": -122.59625244140625, "timestamp": 1764826159, "current_stop_sequence": 7}, {"trip_id": "14724114", "route_id": "6749", "vehicle_id": "14007", "latitude": 49.2318000793457, "longitude": -122.69091796875, "timestamp": 1764826475, "current_stop_sequence": 43}, {"trip_id": "14733689", "route_id": "37810", "vehicle_id": "18044", "latitude": 49.26266860961914, "longitude": -123.24238586425781, "timestamp": 1764826476, "current_stop_sequence": 16}, {"trip_id": "14734247", "route_id": "37807", "vehicle_id": "23007", "latitude": 49.28653335571289, "longitude": -123.1182632446289, "timestamp": 1764826507, "current_stop_sequence": 1}, {"trip_id": "14732428", "route_id": "38311", "vehicle_id": "15012", "latitude": 49.31281661987305, "longitude": -123.07779693603516, "timestamp": 1764826508, "current_stop_sequence": 4}, {"trip_id": "14732489", "route_id": "38311", "vehicle_id": "19031", "latitude": 49.32725143432617, "longitude": -123.13471984863281, "timestamp": 1764826487, "current_stop_sequence": 9}, {"trip_id": "14738041", "route_id": "34542", "vehicle_id": "9568", "latitude": 49.16771697998047, "longitude": -123.13480377197266, "timestamp": 1764826476, "current_stop_sequence": 1}, {"trip_id": "14674944", "route_id": "6617", "vehicle_id": "2111", "latitude": 49.28255081176758, "longitude": -123.1046142578125, "timestamp": 1764826503, "current_stop_sequence": 38}, {"trip_id": "14684062", "route_id": "6633", "vehicle_id": "2271", "latitude": 49.23291778564453, "longitude": -123.12823486328125, "timestamp": 1764826214, "current_stop_sequence": 28}, {"trip_id": "14737795", "route_id": "30055", "vehicle_id": "18318", "latitude": 49.2848014831543, "longitude": -123.14240264892578, "timestamp": 1764826498, "current_stop_sequence": 14}, {"trip_id": "14735821", "route_id": "6619", "vehicle_id": "9450", "latitude": 49.26359939575195, "longitude": -123.13826751708984, "timestamp": 1764826498, "current_stop_sequence": 32}, {"trip_id": "14681923", "route_id": "6627", "vehicle_id": "21025", "latitude": 49.24885177612305, "longitude": -123.01736450195312, "timestamp": 1764826497, "current_stop_sequence": 9}, {"trip_id": "14673160", "route_id": "6614", "vehicle_id": "2151", "latitude": 49.26848220825195, "longitude": -123.17686462402344, "timestamp": 1764826494, "current_stop_sequence": 14}, {"trip_id": "14675467", "route_id": "6618", "vehicle_id": "2502", "latitude": 49.23273468017578, "longitude": -123.09049987792969, "timestamp": 1764826491, "current_stop_sequence": 12}, {"trip_id": "14709408", "route_id": "6705", "vehicle_id": "24144", "latitude": 49.18086624145508, "longitude": -122.845703125, "timestamp": 1764826503, "current_stop_sequence": 5}, {"trip_id": "14698594", "route_id": "30043", "vehicle_id": "21528", "latitude": 49.276668548583984, "longitude": -122.84553527832031, "timestamp": 1764826399, "current_stop_sequence": 30}, {"trip_id": "14734902", "route_id": "46604", "vehicle_id": "19011", "latitude": 49.141117095947266, "longitude": -122.89025115966797, "timestamp": 1764826502, "current_stop_sequence": 6}, {"trip_id": "14734901", "route_id": "46604", "vehicle_id": "18013", "latitude": 49.17431640625, "longitude": -122.89009857177734, "timestamp": 1764826508, "current_stop_sequence": 10}, {"trip_id": "14741764", "route_id": "6651", "vehicle_id": "9670", "latitude": 49.30576705932617, "longitude": -123.02901458740234, "timestamp": 1764826346, "current_stop_sequence": 1}, {"trip_id": "14895779", "route_id": "6780", "vehicle_id": "24543", "latitude": 49.30564880371094, "longitude": -123.02890014648438, "timestamp": 1764826501, "current_stop_sequence": 1}, {"trip_id": "14684886", "route_id": "6636", "vehicle_id": "16206", "latitude": 49.22608184814453, "longitude": -123.11695098876953, "timestamp": 1764826477, "current_stop_sequence": 30}, {"trip_id": "14740963", "route_id": "6612", "vehicle_id": "21002", "latitude": 49.28615188598633, "longitude": -123.11876678466797, "timestamp": 1764826507, "current_stop_sequence": 1}, {"trip_id": "14720239", "route_id": "6738", "vehicle_id": "18384", "latitude": 49.138248443603516, "longitude": -122.73504638671875, "timestamp": 1764826480, "current_stop_sequence": 19}, {"trip_id": "14736846", "route_id": "6615", "vehicle_id": "2133", "latitude": 49.28751754760742, "longitude": -123.12930297851562, "timestamp": 1764826505, "current_stop_sequence": 8}, {"trip_id": "14715007", "route_id": "11692", "vehicle_id": "25109", "latitude": 49.11881637573242, "longitude": -122.7251205444336, "timestamp": 1764826491, "current_stop_sequence": 20}, {"trip_id": "14895415", "route_id": "6687", "vehicle_id": "1203", "latitude": 49.37311553955078, "longitude": -123.27204895019531, "timestamp": 1764826472, "current_stop_sequence": 1}, {"trip_id": "14738905", "route_id": "6727", "vehicle_id": "9415", "latitude": 49.126434326171875, "longitude": -123.18711853027344, "timestamp": 1764826478, "current_stop_sequence": 57}]