[{"trip_id": "14828505", "route_id": "6613", "vehicle_id": "2525", "latitude": 49.284950256347656, "longitude": -123.11128234863281, "timestamp": 1768144102, "current_stop_sequence": 1}, {"trip_id": "14827976", "route_id": "6612", "vehicle_id": "21006", "latitude": 49.28213119506836, "longitude": -123.12476348876953, "timestamp": 1768144115, "current_stop_sequence": 4}, {"trip_id": "14827884", "route_id": "6612", "vehicle_id": "8156", "latitude": 49.2730827331543, "longitude": -123.14413452148438, "timestamp": 1768144102, "current_stop_sequence": 23}, {"trip_id": "14835893", "route_id": "6626", "vehicle_id": "9520", "latitude": 49.28373336791992, "longitude": -123.1131362915039, "timestamp": 1768144134, "current_stop_sequence": 4}, {"trip_id": "14904194", "route_id": "6624", "vehicle_id": "2120", "latitude": 49.282798767089844, "longitude": -123.11178588867188, "timestamp": 1768144098, "current_stop_sequence": 12}, {"trip_id": "14830236", "route_id": "6616", "vehicle_id": "2245", "latitude": 49.28089904785156, "longitude": -123.11101531982422, "timestamp": 1768144000, "current_stop_sequence": 1}, {"trip_id": "14830677", "route_id": "6617", "vehicle_id": "2129", "latitude": 49.28084945678711, "longitude": -123.10594940185547, "timestamp": 1768144089, "current_stop_sequence": 28}, {"trip_id": "14828416", "route_id": "6613", "vehicle_id": "2518", "latitude": 49.22596740722656, "longitude": -123.10153198242188, "timestamp": 1768144101, "current_stop_sequence": 10}, {"trip_id": "14839098", "route_id": "6633", "vehicle_id": "2211", "latitude": 49.23345184326172, "longitude": -123.11163330078125, "timestamp": 1768144133, "current_stop_sequence": 26}, {"trip_id": "14889425", "route_id": "37807", "vehicle_id": "19029", "latitude": 49.28196716308594, "longitude": -123.10693359375, "timestamp": 1768144114, "current_stop_sequence": 13}, {"trip_id": "14833852", "route_id": "6622", "vehicle_id": "2102", "latitude": 49.28193283081055, "longitude": -123.1064682006836, "timestamp": 1768144135, "current_stop_sequence": 40}, {"trip_id": "14835354", "route_id": "6625", "vehicle_id": "2524", "latitude": 49.281768798828125, "longitude": -123.10575103759766, "timestamp": 1768144097, "current_stop_sequence": 43}, {"trip_id": "14832966", "route_id": "16718", "vehicle_id": "2257", "latitude": 49.28441619873047, "longitude": -123.11241912841797, "timestamp": 1768144109, "current_stop_sequence": 23}, {"trip_id": "14828506", "route_id": "6613", "vehicle_id": "2556", "latitude": 49.24065017700195, "longitude": -123.1015853881836, "timestamp": 1768144108, "current_stop_sequence": 21}, {"trip_id": "14828909", "route_id": "6614", "vehicle_id": "2185", "latitude": 49.26806640625, "longitude": -123.21499633789062, "timestamp": 1768144111, "current_stop_sequence": 1}, {"trip_id": "14832840", "route_id": "16718", "vehicle_id": "2165", "latitude": 49.26348114013672, "longitude": -123.1868667602539, "timestamp": 1768144114, "current_stop_sequence": 14}, {"trip_id": "14827975", "route_id": "6612", "vehicle_id": "21018", "latitude": 49.23481750488281, "longitude": -123.18373107910156, "timestamp": 1768144114, "current_stop_sequence": 31}, {"trip_id": "14839097", "route_id": "6633", "vehicle_id": "2127", "latitude": 49.2348518371582, "longitude": -123.18485260009766, "timestamp": 1768144102, "current_stop_sequence": 44}, {"trip_id": "14834307", "route_id": "6623", "vehicle_id": "2110", "latitude": 49.256168365478516, "longitude": -123.12733459472656, "timestamp": 1768144126, "current_stop_sequence": 17}, {"trip_id": "14839018", "route_id": "6633", "vehicle_id": "2250", "latitude": 49.23460006713867, "longitude": -123.15769958496094, "timestamp": 1768144102, "current_stop_sequence": 12}, {"trip_id": "14830617", "route_id": "6617", "vehicle_id": "2208", "latitude": 49.27256774902344, "longitude": -123.13301849365234, "timestamp": 1768144143, "current_stop_sequence": 28}, {"trip_id": "14855832", "route_id": "6672", "vehicle_id": "9640", "latitude": 49.28508377075195, "longitude": -123.12039947509766, "timestamp": 1768144127, "current_stop_sequence": 1}, {"trip_id": "14833330", "route_id": "6621", "vehicle_id": "9448", "latitude": 49.23456573486328, "longitude": -123.11634826660156, "timestamp": 1768144105, "current_stop_sequence": 15}, {"trip_id": "14828977", "route_id": "6614", "vehicle_id": "2153", "latitude": 49.28776550292969, "longitude": -123.04483032226562, "timestamp": 1768143731, "current_stop_sequence": 1}, {"trip_id": "14900044", "route_id": "6641", "vehicle_id": "23009", "latitude": 49.26371765136719, "longitude": -123.1455307006836, "timestamp": 1768144142, "current_stop_sequence": 13}, {"trip_id": "14832965", "route_id": "16718", "vehicle_id": "2164", "latitude": 49.2642822265625, "longitude": -123.18596649169922, "timestamp": 1768144109, "current_stop_sequence": 44}, {"trip_id": "14901419", "route_id": "6619", "vehicle_id": "9450", "latitude": 49.26435089111328, "longitude": -123.1828842163086, "timestamp": 1768143910, "current_stop_sequence": 43}, {"trip_id": "14828947", "route_id": "6614", "vehicle_id": "2278", "latitude": 49.26846694946289, "longitude": -123.17507934570312, "timestamp": 1768144101, "current_stop_sequence": 38}, {"trip_id": "14829474", "route_id": "6615", "vehicle_id": "2205", "latitude": 49.28710174560547, "longitude": -123.14146423339844, "timestamp": 1768144131, "current_stop_sequence": 1}, {"trip_id": "14834308", "route_id": "6623", "vehicle_id": "2166", "latitude": 49.27914810180664, "longitude": -123.11631774902344, "timestamp": 1768144094, "current_stop_sequence": 1}, {"trip_id": "14830618", "route_id": "6617", "vehicle_id": "2158", "latitude": 49.234649658203125, "longitude": -123.18598175048828, "timestamp": 1768144101, "current_stop_sequence": 1}, {"trip_id": "14830678", "route_id": "6617", "vehicle_id": "2273", "latitude": 49.24848175048828, "longitude": -123.05549621582031, "timestamp": 1768144105, "current_stop_sequence": 1}, {"trip_id": "14888735", "route_id": "37810", "vehicle_id": "19004", "latitude": 49.232818603515625, "longitude": -123.07791900634766, "timestamp": 1768144115, "current_stop_sequence": 6}, {"trip_id": "14834236", "route_id": "6623", "vehicle_id": "2136", "latitude": 49.215049743652344, "longitude": -123.12991333007812, "timestamp": 1768144105, "current_stop_sequence": 8}, {"trip_id": "14886089", "route_id": "6834", "vehicle_id": "9514", "latitude": 49.26303482055664, "longitude": -123.09976959228516, "timestamp": 1768144144, "current_stop_sequence": 15}, {"trip_id": "14901324", "route_id": "6619", "vehicle_id": "18342", "latitude": 49.262451171875, "longitude": -123.09211730957031, "timestamp": 1768144089, "current_stop_sequence": 23}, {"trip_id": "14831104", "route_id": "6618", "vehicle_id": "2573", "latitude": 49.2487678527832, "longitude": -123.0902328491211, "timestamp": 1768144118, "current_stop_sequence": 22}, {"trip_id": "14888637", "route_id": "37810", "vehicle_id": "18061", "latitude": 49.23361587524414, "longitude": -123.11783599853516, "timestamp": 1768144089, "current_stop_sequence": 8}, {"trip_id": "14831247", "route_id": "6618", "vehicle_id": "2521", "latitude": 49.2406005859375, "longitude": -123.09021759033203, "timestamp": 1768144113, "current_stop_sequence": 16}, {"trip_id": "14886335", "route_id": "6841", "vehicle_id": "18181", "latitude": 49.26278305053711, "longitude": -123.09980010986328, "timestamp": 1768144099, "current_stop_sequence": 15}, {"trip_id": "14901421", "route_id": "6619", "vehicle_id": "9461", "latitude": 49.26533126831055, "longitude": -123.02498626708984, "timestamp": 1768144101, "current_stop_sequence": 1}, {"trip_id": "14901325", "route_id": "6619", "vehicle_id": "18399", "latitude": 49.26358413696289, "longitude": -123.14068603515625, "timestamp": 1768144107, "current_stop_sequence": 1}, {"trip_id": "14833777", "route_id": "6622", "vehicle_id": "2269", "latitude": 49.281131744384766, "longitude": -123.07018280029297, "timestamp": 1768144092, "current_stop_sequence": 48}, {"trip_id": "14832814", "route_id": "16718", "vehicle_id": "2201", "latitude": 49.281898498535156, "longitude": -123.06900024414062, "timestamp": 1768144117, "current_stop_sequence": 22}, {"trip_id": "14832967", "route_id": "16718", "vehicle_id": "2209", "latitude": 49.28118133544922, "longitude": -123.02690124511719, "timestamp": 1768144137, "current_stop_sequence": 1}, {"trip_id": "14833267", "route_id": "6621", "vehicle_id": "18338", "latitude": 49.2264518737793, "longitude": -123.11631774902344, "timestamp": 1768144144, "current_stop_sequence": 6}, {"trip_id": "14886350", "route_id": "6841", "vehicle_id": "16047", "latitude": 49.27690124511719, "longitude": -123.12446594238281, "timestamp": 1768144106, "current_stop_sequence": 82}, {"trip_id": "14833779", "route_id": "6622", "vehicle_id": "2216", "latitude": 49.21388244628906, "longitude": -123.14088439941406, "timestamp": 1768143889, "current_stop_sequence": 1}, {"trip_id": "14833778", "route_id": "6622", "vehicle_id": "2125", "latitude": 49.260616302490234, "longitude": -123.15301513671875, "timestamp": 1768144089, "current_stop_sequence": 23}, {"trip_id": "14833854", "route_id": "6622", "vehicle_id": "2114", "latitude": 49.23798370361328, "longitude": -123.04834747314453, "timestamp": 1768144114, "current_stop_sequence": 1}, {"trip_id": "14833853", "route_id": "6622", "vehicle_id": "2235", "latitude": 49.25965118408203, "longitude": -123.04419708251953, "timestamp": 1768144113, "current_stop_sequence": 14}, {"trip_id": "14833851", "route_id": "6622", "vehicle_id": "2124", "latitude": 49.26036834716797, "longitude": -123.15315246582031, "timestamp": 1768144111, "current_stop_sequence": 56}, {"trip_id": "14839017", "route_id": "6633", "vehicle_id": "2183", "latitude": 49.232784271240234, "longitude": -123.05411529541016, "timestamp": 1768144093, "current_stop_sequence": 40}, {"trip_id": "14904193", "route_id": "6624", "vehicle_id": "2213", "latitude": 49.25266647338867, "longitude": -123.081298828125, "timestamp": 1768144142, "current_stop_sequence": 30}, {"trip_id": "14904293", "route_id": "6624", "vehicle_id": "2116", "latitude": 49.225650787353516, "longitude": -123.00348663330078, "timestamp": 1768144110, "current_stop_sequence": 1}, {"trip_id": "14904292", "route_id": "6624", "vehicle_id": "2141", "latitude": 49.23453140258789, "longitude": -123.03636932373047, "timestamp": 1768144102, "current_stop_sequence": 1}, {"trip_id": "14904291", "route_id": "6624", "vehicle_id": "2253", "latitude": 49.26001739501953, "longitude": -123.09656524658203, "timestamp": 1768144102, "current_stop_sequence": 27}, {"trip_id": "14835353", "route_id": "6625", "vehicle_id": "2507", "latitude": 49.26250076293945, "longitude": -123.0696792602539, "timestamp": 1768144093, "current_stop_sequence": 23}, {"trip_id": "14835446", "route_id": "6625", "vehicle_id": "2554", "latitude": 49.27901840209961, "longitude": -123.07051849365234, "timestamp": 1768144123, "current_stop_sequence": 20}, {"trip_id": "14835445", "route_id": "6625", "vehicle_id": "2541", "latitude": 49.212581634521484, "longitude": -123.06610107421875, "timestamp": 1768144071, "current_stop_sequence": 50}, {"trip_id": "14835913", "route_id": "6626", "vehicle_id": "18398", "latitude": 49.2419319152832, "longitude": -123.076416015625, "timestamp": 1768144088, "current_stop_sequence": 31}, {"trip_id": "14835979", "route_id": "6626", "vehicle_id": "18319", "latitude": 49.221717834472656, "longitude": -123.07734680175781, "timestamp": 1768144100, "current_stop_sequence": 5}, {"trip_id": "14835965", "route_id": "6626", "vehicle_id": "9485", "latitude": 49.276649475097656, "longitude": -123.09306335449219, "timestamp": 1768144092, "current_stop_sequence": 34}, {"trip_id": "14847440", "route_id": "6651", "vehicle_id": "9622", "latitude": 49.2810173034668, "longitude": -123.02466583251953, "timestamp": 1768144100, "current_stop_sequence": 1}, {"trip_id": "14889272", "route_id": "37807", "vehicle_id": "19042", "latitude": 49.28091812133789, "longitude": -122.99545288085938, "timestamp": 1768144106, "current_stop_sequence": 10}, {"trip_id": "14846380", "route_id": "6649", "vehicle_id": "9498", "latitude": 49.25471878051758, "longitude": -123.00261688232422, "timestamp": 1768144089, "current_stop_sequence": 33}, {"trip_id": "14858563", "route_id": "6682", "vehicle_id": "9779", "latitude": 49.301448822021484, "longitude": -123.14413452148438, "timestamp": 1768144133, "current_stop_sequence": 7}, {"trip_id": "14861259", "route_id": "6693", "vehicle_id": "8144", "latitude": 49.295684814453125, "longitude": -123.13638305664062, "timestamp": 1768144107, "current_stop_sequence": 4}, {"trip_id": "14836888", "route_id": "6627", "vehicle_id": "21004", "latitude": 49.25798416137695, "longitude": -123.19187927246094, "timestamp": 1768144099, "current_stop_sequence": 11}, {"trip_id": "14846873", "route_id": "6650", "vehicle_id": "25118", "latitude": 49.248783111572266, "longitude": -123.0193862915039, "timestamp": 1768144141, "current_stop_sequence": 16}, {"trip_id": "14836936", "route_id": "6627", "vehicle_id": "21023", "latitude": 49.24869918823242, "longitude": -123.0911865234375, "timestamp": 1768144108, "current_stop_sequence": 30}, {"trip_id": "14839865", "route_id": "6636", "vehicle_id": "12006", "latitude": 49.26521682739258, "longitude": -123.2444839477539, "timestamp": 1768144094, "current_stop_sequence": 61}, {"trip_id": "14838136", "route_id": "6631", "vehicle_id": "9724", "latitude": 49.244632720947266, "longitude": -123.04946899414062, "timestamp": 1768144107, "current_stop_sequence": 1}, {"trip_id": "14888636", "route_id": "37810", "vehicle_id": "18028", "latitude": 49.23725128173828, "longitude": -123.03279876708984, "timestamp": 1768143775, "current_stop_sequence": 16}, {"trip_id": "14839016", "route_id": "6633", "vehicle_id": "2115", "latitude": 49.23833465576172, "longitude": -123.03191375732422, "timestamp": 1768143725, "current_stop_sequence": 48}, {"trip_id": "14837261", "route_id": "6628", "vehicle_id": "9747", "latitude": 49.22003173828125, "longitude": -123.0238037109375, "timestamp": 1768144138, "current_stop_sequence": 14}, {"trip_id": "14837839", "route_id": "6630", "vehicle_id": "9660", "latitude": 49.23871612548828, "longitude": -123.03286743164062, "timestamp": 1768144143, "current_stop_sequence": 1}, {"trip_id": "14837546", "route_id": "6629", "vehicle_id": "9627", "latitude": 49.275482177734375, "longitude": -123.03368377685547, "timestamp": 1768144144, "current_stop_sequence": 5}, {"trip_id": "14837861", "route_id": "6630", "vehicle_id": "9728", "latitude": 49.28343200683594, "longitude": -123.0313491821289, "timestamp": 1768144091, "current_stop_sequence": 6}, {"trip_id": "14837878", "route_id": "6630", "vehicle_id": "9633", "latitude": 49.24665069580078, "longitude": -123.0198974609375, "timestamp": 1768144121, "current_stop_sequence": 23}, {"trip_id": "14889382", "route_id": "37807", "vehicle_id": "22005", "latitude": 49.280433654785156, "longitude": -122.97086334228516, "timestamp": 1768144104, "current_stop_sequence": 4}, {"trip_id": "14888638", "route_id": "37810", "vehicle_id": "19003", "latitude": 49.2348518371582, "longitude": -123.19673156738281, "timestamp": 1768144092, "current_stop_sequence": 3}, {"trip_id": "14888734", "route_id": "37810", "vehicle_id": "18016", "latitude": 49.234798431396484, "longitude": -123.19194793701172, "timestamp": 1768144131, "current_stop_sequence": 14}, {"trip_id": "14839785", "route_id": "6636", "vehicle_id": "16205", "latitude": 49.22200012207031, "longitude": -123.02507019042969, "timestamp": 1768144097, "current_stop_sequence": 30}, {"trip_id": "14839866", "route_id": "6636", "vehicle_id": "16216", "latitude": 49.225433349609375, "longitude": -123.08733367919922, "timestamp": 1768144090, "current_stop_sequence": 27}, {"trip_id": "14839856", "route_id": "6636", "vehicle_id": "12009", "latitude": 49.228431701660156, "longitude": -123.17423248291016, "timestamp": 1768144115, "current_stop_sequence": 48}, {"trip_id": "14900045", "route_id": "6641", "vehicle_id": "16226", "latitude": 49.26333236694336, "longitude": -123.02881622314453, "timestamp": 1768144114, "current_stop_sequence": 1}, {"trip_id": "14902813", "route_id": "6620", "vehicle_id": "2508", "latitude": 49.2095832824707, "longitude": -123.11605072021484, "timestamp": 1768144083, "current_stop_sequence": 35}, {"trip_id": "14842392", "route_id": "6642", "vehicle_id": "25109", "latitude": 49.2109489440918, "longitude": -123.0714340209961, "timestamp": 1768144133, "current_stop_sequence": 14}, {"trip_id": "14842389", "route_id": "6642", "vehicle_id": "25146", "latitude": 49.205467224121094, "longitude": -122.97848510742188, "timestamp": 1768144101, "current_stop_sequence": 34}, {"trip_id": "14905273", "route_id": "6663", "vehicle_id": "14027", "latitude": 49.19951629638672, "longitude": -122.95011901855469, "timestamp": 1768144081, "current_stop_sequence": 1}, {"trip_id": "14842480", "route_id": "6642", "vehicle_id": "9508", "latitude": 49.21113204956055, "longitude": -123.07344818115234, "timestamp": 1768144126, "current_stop_sequence": 23}, {"trip_id": "14828507", "route_id": "6613", "vehicle_id": "2558", "latitude": 49.20976638793945, "longitude": -123.11519622802734, "timestamp": 1768144098, "current_stop_sequence": 37}, {"trip_id": "14873685", "route_id": "6728", "vehicle_id": "9483", "latitude": 49.19838333129883, "longitude": -122.94879913330078, "timestamp": 1768144103, "current_stop_sequence": 1}, {"trip_id": "14906044", "route_id": "6662", "vehicle_id": "16039", "latitude": 49.20553207397461, "longitude": -122.9433822631836, "timestamp": 1768144135, "current_stop_sequence": 19}, {"trip_id": "14864174", "route_id": "6705", "vehicle_id": "9683", "latitude": 49.20140075683594, "longitude": -122.9113998413086, "timestamp": 1768143969, "current_stop_sequence": 1}, {"trip_id": "14845845", "route_id": "32799", "vehicle_id": "9437", "latitude": 49.22916793823242, "longitude": -123.00223541259766, "timestamp": 1768144107, "current_stop_sequence": 3}, {"trip_id": "14886071", "route_id": "6834", "vehicle_id": "9436", "latitude": 49.22835159301758, "longitude": -122.99961853027344, "timestamp": 1768144097, "current_stop_sequence": 48}, {"trip_id": "14844472", "route_id": "6645", "vehicle_id": "9492", "latitude": 49.21514892578125, "longitude": -122.95731353759766, "timestamp": 1768144108, "current_stop_sequence": 22}, {"trip_id": "14844427", "route_id": "6645", "vehicle_id": "25183", "latitude": 49.20954895019531, "longitude": -122.91584777832031, "timestamp": 1768144114, "current_stop_sequence": 19}, {"trip_id": "14845197", "route_id": "6647", "vehicle_id": "25124", "latitude": 49.21626663208008, "longitude": -122.94308471679688, "timestamp": 1768144115, "current_stop_sequence": 4}, {"trip_id": "14845233", "route_id": "6647", "vehicle_id": "25117", "latitude": 49.212650299072266, "longitude": -122.95858001708984, "timestamp": 1768143893, "current_stop_sequence": 17}, {"trip_id": "14839857", "route_id": "6636", "vehicle_id": "12018", "latitude": 49.22198486328125, "longitude": -123.00945281982422, "timestamp": 1768144144, "current_stop_sequence": 5}, {"trip_id": "14889431", "route_id": "37807", "vehicle_id": "19025", "latitude": 49.281150817871094, "longitude": -123.0311508178711, "timestamp": 1768144103, "current_stop_sequence": 2}, {"trip_id": "14848307", "route_id": "6654", "vehicle_id": "21548", "latitude": 49.267948150634766, "longitude": -122.95093536376953, "timestamp": 1768144134, "current_stop_sequence": 15}, {"trip_id": "14847933", "route_id": "33292", "vehicle_id": "25158", "latitude": 49.212215423583984, "longitude": -122.95833587646484, "timestamp": 1768143903, "current_stop_sequence": 1}, {"trip_id": "14850134", "route_id": "6659", "vehicle_id": "16007", "latitude": 49.27531814575195, "longitude": -122.79865264892578, "timestamp": 1768144115, "current_stop_sequence": 1}, {"trip_id": "14887945", "route_id": "37809", "vehicle_id": "18060", "latitude": 49.27621841430664, "longitude": -122.79703521728516, "timestamp": 1768144088, "current_stop_sequence": 7}, {"trip_id": "14854638", "route_id": "30049", "vehicle_id": "21517", "latitude": 49.277950286865234, "longitude": -122.79557037353516, "timestamp": 1768144113, "current_stop_sequence": 1}, {"trip_id": "14848693", "route_id": "6657", "vehicle_id": "25116", "latitude": 49.22985076904297, "longitude": -122.98898315429688, "timestamp": 1768144143, "current_stop_sequence": 6}, {"trip_id": "14889364", "route_id": "37807", "vehicle_id": "16220", "latitude": 49.27851867675781, "longitude": -122.91273498535156, "timestamp": 1768144106, "current_stop_sequence": 1}, {"trip_id": "14889374", "route_id": "37807", "vehicle_id": "19020", "latitude": 49.28241729736328, "longitude": -123.09961700439453, "timestamp": 1768144114, "current_stop_sequence": 1}, {"trip_id": "14905787", "route_id": "6663", "vehicle_id": "16031", "latitude": 49.231048583984375, "longitude": -122.8927993774414, "timestamp": 1768144140, "current_stop_sequence": 4}, {"trip_id": "14853415", "route_id": "30043", "vehicle_id": "21530", "latitude": 49.25920104980469, "longitude": -122.8927001953125, "timestamp": 1768144131, "current_stop_sequence": 6}, {"trip_id": "14853933", "route_id": "30046", "vehicle_id": "24526", "latitude": 49.27656555175781, "longitude": -122.83885192871094, "timestamp": 1768144112, "current_stop_sequence": 3}, {"trip_id": "14878876", "route_id": "6749", "vehicle_id": "14001", "latitude": 49.27451705932617, "longitude": -122.79329681396484, "timestamp": 1768144098, "current_stop_sequence": 1}, {"trip_id": "14854896", "route_id": "30050", "vehicle_id": "24533", "latitude": 49.275299072265625, "longitude": -122.79886627197266, "timestamp": 1768144085, "current_stop_sequence": 1}, {"trip_id": "14851192", "route_id": "6665", "vehicle_id": "24509", "latitude": 49.250850677490234, "longitude": -122.8524169921875, "timestamp": 1768144098, "current_stop_sequence": 16}, {"trip_id": "14831203", "route_id": "6618", "vehicle_id": "2540", "latitude": 49.28144836425781, "longitude": -123.10393524169922, "timestamp": 1768144115, "current_stop_sequence": 38}, {"trip_id": "14852013", "route_id": "6668", "vehicle_id": "14045", "latitude": 49.253631591796875, "longitude": -122.80281829833984, "timestamp": 1768144100, "current_stop_sequence": 11}, {"trip_id": "14852018", "route_id": "6668", "vehicle_id": "18170", "latitude": 49.244117736816406, "longitude": -122.80905151367188, "timestamp": 1768144091, "current_stop_sequence": 8}, {"trip_id": "14850584", "route_id": "6661", "vehicle_id": "24525", "latitude": 49.26161575317383, "longitude": -122.84086608886719, "timestamp": 1768144102, "current_stop_sequence": 15}, {"trip_id": "14851391", "route_id": "6666", "vehicle_id": "14013", "latitude": 49.23540115356445, "longitude": -122.77771759033203, "timestamp": 1768144105, "current_stop_sequence": 18}, {"trip_id": "14851772", "route_id": "6667", "vehicle_id": "18182", "latitude": 49.260982513427734, "longitude": -122.77401733398438, "timestamp": 1768143902, "current_stop_sequence": 1}, {"trip_id": "14853104", "route_id": "30040", "vehicle_id": "21532", "latitude": 49.283382415771484, "longitude": -122.77136993408203, "timestamp": 1768144141, "current_stop_sequence": 17}, {"trip_id": "14853958", "route_id": "30046", "vehicle_id": "21527", "latitude": 49.27583312988281, "longitude": -122.79893493652344, "timestamp": 1768144024, "current_stop_sequence": 1}, {"trip_id": "14855391", "route_id": "30051", "vehicle_id": "21561", "latitude": 49.28726577758789, "longitude": -122.783935546875, "timestamp": 1768144110, "current_stop_sequence": 5}, {"trip_id": "14855872", "route_id": "6672", "vehicle_id": "9787", "latitude": 49.313682556152344, "longitude": -123.04033660888672, "timestamp": 1768144120, "current_stop_sequence": 19}, {"trip_id": "14858630", "route_id": "6682", "vehicle_id": "9605", "latitude": 49.32828140258789, "longitude": -123.05471801757812, "timestamp": 1768144115, "current_stop_sequence": 4}, {"trip_id": "14856038", "route_id": "6673", "vehicle_id": "9725", "latitude": 49.30794906616211, "longitude": -122.95311737060547, "timestamp": 1768144110, "current_stop_sequence": 19}, {"trip_id": "14857206", "route_id": "6676", "vehicle_id": "9714", "latitude": 49.33815002441406, "longitude": -123.0361328125, "timestamp": 1768144100, "current_stop_sequence": 9}, {"trip_id": "15070065", "route_id": "6692", "vehicle_id": "1605", "latitude": 49.31341552734375, "longitude": -123.0470962524414, "timestamp": 1768144105, "current_stop_sequence": 8}, {"trip_id": "15070021", "route_id": "6692", "vehicle_id": "1610", "latitude": 49.326866149902344, "longitude": -123.13829803466797, "timestamp": 1768144107, "current_stop_sequence": 14}, {"trip_id": "14886183", "route_id": "6837", "vehicle_id": "9654", "latitude": 49.323848724365234, "longitude": -123.11681365966797, "timestamp": 1768144139, "current_stop_sequence": 9}, {"trip_id": "14858561", "route_id": "6682", "vehicle_id": "9786", "latitude": 49.280616760253906, "longitude": -123.1156005859375, "timestamp": 1768143794, "current_stop_sequence": 1}, {"trip_id": "14858564", "route_id": "6682", "vehicle_id": "9768", "latitude": 49.32194900512695, "longitude": -123.06189727783203, "timestamp": 1768144145, "current_stop_sequence": 25}, {"trip_id": "15070167", "route_id": "6687", "vehicle_id": "705", "latitude": 49.36393356323242, "longitude": -123.27733612060547, "timestamp": 1768144142, "current_stop_sequence": 6}, {"trip_id": "15070022", "route_id": "6692", "vehicle_id": "904", "latitude": 49.33563232421875, "longitude": -123.1810302734375, "timestamp": 1768144108, "current_stop_sequence": 1}, {"trip_id": "15070252", "route_id": "6687", "vehicle_id": "701", "latitude": 49.341800689697266, "longitude": -123.23088073730469, "timestamp": 1768144122, "current_stop_sequence": 36}, {"trip_id": "14878544", "route_id": "6748", "vehicle_id": "18367", "latitude": 49.146183013916016, "longitude": -123.00226593017578, "timestamp": 1768144126, "current_stop_sequence": 24}, {"trip_id": "14886344", "route_id": "6841", "vehicle_id": "14026", "latitude": 49.27961730957031, "longitude": -123.12471771240234, "timestamp": 1768144095, "current_stop_sequence": 5}, {"trip_id": "14868660", "route_id": "6715", "vehicle_id": "19401", "latitude": 49.071998596191406, "longitude": -122.8221664428711, "timestamp": 1768144098, "current_stop_sequence": 3}, {"trip_id": "14863145", "route_id": "6703", "vehicle_id": "9696", "latitude": 49.203617095947266, "longitude": -122.87608337402344, "timestamp": 1768143993, "current_stop_sequence": 30}, {"trip_id": "14861952", "route_id": "6698", "vehicle_id": "21406", "latitude": 49.15589904785156, "longitude": -122.90032958984375, "timestamp": 1768144119, "current_stop_sequence": 10}, {"trip_id": "14863146", "route_id": "6703", "vehicle_id": "16106", "latitude": 49.17380142211914, "longitude": -122.89009857177734, "timestamp": 1768144095, "current_stop_sequence": 23}, {"trip_id": "14890008", "route_id": "46604", "vehicle_id": "18031", "latitude": 49.160850524902344, "longitude": -122.89046478271484, "timestamp": 1768144102, "current_stop_sequence": 5}, {"trip_id": "14863220", "route_id": "6703", "vehicle_id": "18363", "latitude": 49.134281158447266, "longitude": -122.88480377197266, "timestamp": 1768144138, "current_stop_sequence": 19}, {"trip_id": "14867310", "route_id": "6713", "vehicle_id": "19413", "latitude": 49.13123321533203, "longitude": -122.89026641845703, "timestamp": 1768144104, "current_stop_sequence": 12}, {"trip_id": "14874713", "route_id": "6737", "vehicle_id": "9673", "latitude": 49.189048767089844, "longitude": -122.84913635253906, "timestamp": 1768144097, "current_stop_sequence": 1}, {"trip_id": "14863594", "route_id": "6704", "vehicle_id": "19137", "latitude": 49.19148254394531, "longitude": -122.84046936035156, "timestamp": 1768144098, "current_stop_sequence": 4}, {"trip_id": "14886792", "route_id": "37808", "vehicle_id": "18003", "latitude": 49.1914176940918, "longitude": -122.81161499023438, "timestamp": 1768144128, "current_stop_sequence": 11}, {"trip_id": "14875622", "route_id": "23384", "vehicle_id": "18369", "latitude": 49.14794921875, "longitude": -122.75662994384766, "timestamp": 1768144123, "current_stop_sequence": 8}, {"trip_id": "14875091", "route_id": "6738", "vehicle_id": "24133", "latitude": 49.14753341674805, "longitude": -122.75585174560547, "timestamp": 1768144127, "current_stop_sequence": 17}, {"trip_id": "14867849", "route_id": "29038", "vehicle_id": "16127", "latitude": 49.10416793823242, "longitude": -122.70764923095703, "timestamp": 1768144090, "current_stop_sequence": 13}, {"trip_id": "14875183", "route_id": "6738", "vehicle_id": "19120", "latitude": 49.15370178222656, "longitude": -122.76959991455078, "timestamp": 1768144091, "current_stop_sequence": 18}, {"trip_id": "14870545", "route_id": "7321", "vehicle_id": "24102", "latitude": 49.053565979003906, "longitude": -122.8011474609375, "timestamp": 1768144092, "current_stop_sequence": 17}, {"trip_id": "14865274", "route_id": "6706", "vehicle_id": "15010", "latitude": 49.13359832763672, "longitude": -122.84030151367188, "timestamp": 1768143714, "current_stop_sequence": 34}, {"trip_id": "14865878", "route_id": "6708", "vehicle_id": "18133", "latitude": 49.13361740112305, "longitude": -122.83978271484375, "timestamp": 1768144114, "current_stop_sequence": 25}, {"trip_id": "14864245", "route_id": "6705", "vehicle_id": "24120", "latitude": 49.14678192138672, "longitude": -122.84559631347656, "timestamp": 1768144131, "current_stop_sequence": 43}, {"trip_id": "14886809", "route_id": "37808", "vehicle_id": "18029", "latitude": 49.157249450683594, "longitude": -122.84566497802734, "timestamp": 1768144123, "current_stop_sequence": 3}, {"trip_id": "14864276", "route_id": "6705", "vehicle_id": "24128", "latitude": 49.15119934082031, "longitude": -122.8458480834961, "timestamp": 1768144140, "current_stop_sequence": 15}, {"trip_id": "14886880", "route_id": "37808", "vehicle_id": "19012", "latitude": 49.13290023803711, "longitude": -122.84284973144531, "timestamp": 1768143934, "current_stop_sequence": 12}, {"trip_id": "14863219", "route_id": "6703", "vehicle_id": "24118", "latitude": 49.13349914550781, "longitude": -122.8440170288086, "timestamp": 1768143739, "current_stop_sequence": 27}, {"trip_id": "14864298", "route_id": "6705", "vehicle_id": "18107", "latitude": 49.091800689697266, "longitude": -122.81766510009766, "timestamp": 1768144107, "current_stop_sequence": 33}, {"trip_id": "14864272", "route_id": "6705", "vehicle_id": "19130", "latitude": 49.05571746826172, "longitude": -122.8062973022461, "timestamp": 1768144091, "current_stop_sequence": 41}, {"trip_id": "14876003", "route_id": "18705", "vehicle_id": "18388", "latitude": 49.03278350830078, "longitude": -122.80108642578125, "timestamp": 1768144138, "current_stop_sequence": 53}, {"trip_id": "14861985", "route_id": "6698", "vehicle_id": "21418", "latitude": 49.13399887084961, "longitude": -122.87840270996094, "timestamp": 1768144137, "current_stop_sequence": 4}, {"trip_id": "14865205", "route_id": "6706", "vehicle_id": "15021", "latitude": 49.1414680480957, "longitude": -122.86783599853516, "timestamp": 1768144102, "current_stop_sequence": 13}, {"trip_id": "14865235", "route_id": "6706", "vehicle_id": "18383", "latitude": 49.182716369628906, "longitude": -122.86766815185547, "timestamp": 1768144144, "current_stop_sequence": 25}, {"trip_id": "14865563", "route_id": "6707", "vehicle_id": "7476", "latitude": 49.190101623535156, "longitude": -122.84989929199219, "timestamp": 1768144089, "current_stop_sequence": 30}, {"trip_id": "14865272", "route_id": "6706", "vehicle_id": "15002", "latitude": 49.189048767089844, "longitude": -122.84856414794922, "timestamp": 1768144114, "current_stop_sequence": 1}, {"trip_id": "14865295", "route_id": "6706", "vehicle_id": "7468", "latitude": 49.18989944458008, "longitude": -122.84980010986328, "timestamp": 1768144126, "current_stop_sequence": 1}, {"trip_id": "14865273", "route_id": "6706", "vehicle_id": "15005", "latitude": 49.14099884033203, "longitude": -122.86669921875, "timestamp": 1768144100, "current_stop_sequence": 25}, {"trip_id": "14865620", "route_id": "6707", "vehicle_id": "19133", "latitude": 49.176666259765625, "longitude": -122.85693359375, "timestamp": 1768144111, "current_stop_sequence": 7}, {"trip_id": "14865857", "route_id": "6708", "vehicle_id": "19109", "latitude": 49.1633186340332, "longitude": -122.83453369140625, "timestamp": 1768144143, "current_stop_sequence": 15}, {"trip_id": "14875182", "route_id": "6738", "vehicle_id": "16107", "latitude": 49.18083190917969, "longitude": -122.841064453125, "timestamp": 1768144088, "current_stop_sequence": 26}, {"trip_id": "14875749", "route_id": "23384", "vehicle_id": "16102", "latitude": 49.18146514892578, "longitude": -122.8453140258789, "timestamp": 1768144095, "current_stop_sequence": 47}, {"trip_id": "14865877", "route_id": "6708", "vehicle_id": "24142", "latitude": 49.188682556152344, "longitude": -122.84860229492188, "timestamp": 1768143903, "current_stop_sequence": 1}, {"trip_id": "14866837", "route_id": "17707", "vehicle_id": "24138", "latitude": 49.19150161743164, "longitude": -122.77050018310547, "timestamp": 1768144141, "current_stop_sequence": 12}, {"trip_id": "14842530", "route_id": "6642", "vehicle_id": "25157", "latitude": 49.19969940185547, "longitude": -122.9496841430664, "timestamp": 1768144103, "current_stop_sequence": 1}, {"trip_id": "14867839", "route_id": "29038", "vehicle_id": "9667", "latitude": 49.11854934692383, "longitude": -122.82337951660156, "timestamp": 1768144144, "current_stop_sequence": 9}, {"trip_id": "14889913", "route_id": "46604", "vehicle_id": "19008", "latitude": 49.133949279785156, "longitude": -122.86761474609375, "timestamp": 1768144098, "current_stop_sequence": 2}, {"trip_id": "14863147", "route_id": "6703", "vehicle_id": "19135", "latitude": 49.133949279785156, "longitude": -122.86688232421875, "timestamp": 1768144095, "current_stop_sequence": 6}, {"trip_id": "14867350", "route_id": "6713", "vehicle_id": "21415", "latitude": 49.11906814575195, "longitude": -122.90274810791016, "timestamp": 1768144130, "current_stop_sequence": 8}, {"trip_id": "14861965", "route_id": "6698", "vehicle_id": "21413", "latitude": 49.17283248901367, "longitude": -122.95386505126953, "timestamp": 1768144138, "current_stop_sequence": 13}, {"trip_id": "14870596", "route_id": "7321", "vehicle_id": "18105", "latitude": 49.12591552734375, "longitude": -122.80118560791016, "timestamp": 1768144107, "current_stop_sequence": 20}, {"trip_id": "14868183", "route_id": "40855", "vehicle_id": "9479", "latitude": 49.05271530151367, "longitude": -122.88227081298828, "timestamp": 1768144101, "current_stop_sequence": 3}, {"trip_id": "14868587", "route_id": "6715", "vehicle_id": "21424", "latitude": 49.091468811035156, "longitude": -122.91400146484375, "timestamp": 1768144130, "current_stop_sequence": 23}, {"trip_id": "14864252", "route_id": "6705", "vehicle_id": "19126", "latitude": 49.027584075927734, "longitude": -122.80239868164062, "timestamp": 1768144097, "current_stop_sequence": 1}, {"trip_id": "14864176", "route_id": "6705", "vehicle_id": "19107", "latitude": 49.02763366699219, "longitude": -122.80464935302734, "timestamp": 1768144121, "current_stop_sequence": 2}, {"trip_id": "14869284", "route_id": "31819", "vehicle_id": "25615", "latitude": 49.03083419799805, "longitude": -122.77908325195312, "timestamp": 1768144114, "current_stop_sequence": 14}, {"trip_id": "14868225", "route_id": "40855", "vehicle_id": "9469", "latitude": 49.03118133544922, "longitude": -122.806884765625, "timestamp": 1768144108, "current_stop_sequence": 2}, {"trip_id": "14862179", "route_id": "6822", "vehicle_id": "19144", "latitude": 49.13743209838867, "longitude": -122.88856506347656, "timestamp": 1768143965, "current_stop_sequence": 1}, {"trip_id": "14872783", "route_id": "6727", "vehicle_id": "9503", "latitude": 49.126468658447266, "longitude": -123.1839828491211, "timestamp": 1768144140, "current_stop_sequence": 1}, {"trip_id": "14871359", "route_id": "6723", "vehicle_id": "9419", "latitude": 49.12691879272461, "longitude": -123.15892028808594, "timestamp": 1768144122, "current_stop_sequence": 23}, {"trip_id": "14871660", "route_id": "6724", "vehicle_id": "9549", "latitude": 49.14891815185547, "longitude": -123.1365966796875, "timestamp": 1768144102, "current_stop_sequence": 22}, {"trip_id": "14871661", "route_id": "6724", "vehicle_id": "9564", "latitude": 49.1348991394043, "longitude": -123.06490325927734, "timestamp": 1768143923, "current_stop_sequence": 1}, {"trip_id": "14871936", "route_id": "6725", "vehicle_id": "9573", "latitude": 49.13501739501953, "longitude": -123.06484985351562, "timestamp": 1768143960, "current_stop_sequence": 1}, {"trip_id": "14877283", "route_id": "6741", "vehicle_id": "21414", "latitude": 49.04201889038086, "longitude": -123.07068634033203, "timestamp": 1768144124, "current_stop_sequence": 19}, {"trip_id": "14878122", "route_id": "6747", "vehicle_id": "21410", "latitude": 49.0498161315918, "longitude": -123.0582504272461, "timestamp": 1768144123, "current_stop_sequence": 3}, {"trip_id": "14872502", "route_id": "34542", "vehicle_id": "9538", "latitude": 49.14103317260742, "longitude": -123.16999816894531, "timestamp": 1768144123, "current_stop_sequence": 15}, {"trip_id": "14872594", "route_id": "34542", "vehicle_id": "9533", "latitude": 49.13908386230469, "longitude": -123.19178009033203, "timestamp": 1768144141, "current_stop_sequence": 25}, {"trip_id": "14873192", "route_id": "34543", "vehicle_id": "9553", "latitude": 49.140750885009766, "longitude": -123.1039810180664, "timestamp": 1768144105, "current_stop_sequence": 12}, {"trip_id": "14873108", "route_id": "34543", "vehicle_id": "9560", "latitude": 49.142799377441406, "longitude": -123.12523651123047, "timestamp": 1768144094, "current_stop_sequence": 13}, {"trip_id": "14873596", "route_id": "6728", "vehicle_id": "25136", "latitude": 49.17770004272461, "longitude": -122.9681167602539, "timestamp": 1768144101, "current_stop_sequence": 29}, {"trip_id": "14867315", "route_id": "6713", "vehicle_id": "21421", "latitude": 49.199615478515625, "longitude": -122.94983673095703, "timestamp": 1768144126, "current_stop_sequence": 1}, {"trip_id": "14871701", "route_id": "6724", "vehicle_id": "9551", "latitude": 49.19053268432617, "longitude": -123.13099670410156, "timestamp": 1768144111, "current_stop_sequence": 2}, {"trip_id": "14874665", "route_id": "6737", "vehicle_id": "9669", "latitude": 49.10615158081055, "longitude": -122.65571594238281, "timestamp": 1768144094, "current_stop_sequence": 1}, {"trip_id": "14875184", "route_id": "6738", "vehicle_id": "24115", "latitude": 49.110084533691406, "longitude": -122.67121887207031, "timestamp": 1768144136, "current_stop_sequence": 5}, {"trip_id": "14874714", "route_id": "6737", "vehicle_id": "16105", "latitude": 49.17696762084961, "longitude": -122.6731185913086, "timestamp": 1768144101, "current_stop_sequence": 17}, {"trip_id": "14875090", "route_id": "6738", "vehicle_id": "9686", "latitude": 49.10744857788086, "longitude": -122.66563415527344, "timestamp": 1768144114, "current_stop_sequence": 30}, {"trip_id": "14876967", "route_id": "12940", "vehicle_id": "18365", "latitude": 49.10641860961914, "longitude": -122.6583023071289, "timestamp": 1768144141, "current_stop_sequence": 1}, {"trip_id": "14863703", "route_id": "6704", "vehicle_id": "18379", "latitude": 49.10618209838867, "longitude": -122.65380096435547, "timestamp": 1768144145, "current_stop_sequence": 1}, {"trip_id": "14875718", "route_id": "23384", "vehicle_id": "19122", "latitude": 49.05315017700195, "longitude": -122.46526336669922, "timestamp": 1768144102, "current_stop_sequence": 8}, {"trip_id": "14877314", "route_id": "6741", "vehicle_id": "21404", "latitude": 49.19106674194336, "longitude": -123.1185302734375, "timestamp": 1768143942, "current_stop_sequence": 1}, {"trip_id": "14851771", "route_id": "6667", "vehicle_id": "18187", "latitude": 49.27830123901367, "longitude": -122.79530334472656, "timestamp": 1768144114, "current_stop_sequence": 9}, {"trip_id": "14887869", "route_id": "37809", "vehicle_id": "18042", "latitude": 49.24306869506836, "longitude": -122.72000122070312, "timestamp": 1768144102, "current_stop_sequence": 4}, {"trip_id": "14878870", "route_id": "6749", "vehicle_id": "18193", "latitude": 49.220516204833984, "longitude": -122.63743591308594, "timestamp": 1768144093, "current_stop_sequence": 25}, {"trip_id": "14878931", "route_id": "6749", "vehicle_id": "14002", "latitude": 49.22031784057617, "longitude": -122.53583526611328, "timestamp": 1768144089, "current_stop_sequence": 1}, {"trip_id": "14868623", "route_id": "6715", "vehicle_id": "19414", "latitude": 49.190765380859375, "longitude": -123.1141357421875, "timestamp": 1768144108, "current_stop_sequence": 25}, {"trip_id": "14840300", "route_id": "6637", "vehicle_id": "18335", "latitude": 49.27939987182617, "longitude": -123.10511779785156, "timestamp": 1768143866, "current_stop_sequence": 1}, {"trip_id": "14850347", "route_id": "6660", "vehicle_id": "18200", "latitude": 49.25571823120117, "longitude": -122.81580352783203, "timestamp": 1768144111, "current_stop_sequence": 12}, {"trip_id": "14861258", "route_id": "6693", "vehicle_id": "23001", "latitude": 49.37156677246094, "longitude": -123.27397918701172, "timestamp": 1768144122, "current_stop_sequence": 7}, {"trip_id": "14848128", "route_id": "6652", "vehicle_id": "21558", "latitude": 49.258968353271484, "longitude": -122.96414947509766, "timestamp": 1768143755, "current_stop_sequence": 1}, {"trip_id": "14850952", "route_id": "6664", "vehicle_id": "16020", "latitude": 49.24773406982422, "longitude": -122.89544677734375, "timestamp": 1768144079, "current_stop_sequence": 1}, {"trip_id": "14837825", "route_id": "6630", "vehicle_id": "9756", "latitude": 49.26459884643555, "longitude": -123.01432037353516, "timestamp": 1768144136, "current_stop_sequence": 20}, {"trip_id": "14886342", "route_id": "6841", "vehicle_id": "18191", "latitude": 49.249717712402344, "longitude": -122.89994812011719, "timestamp": 1768144108, "current_stop_sequence": 50}, {"trip_id": "14875658", "route_id": "23384", "vehicle_id": "16118", "latitude": 49.107967376708984, "longitude": -122.66680145263672, "timestamp": 1768144108, "current_stop_sequence": 13}, {"trip_id": "14875745", "route_id": "23384", "vehicle_id": "19111", "latitude": 49.119232177734375, "longitude": -122.69196319580078, "timestamp": 1768144145, "current_stop_sequence": 36}, {"trip_id": "14876004", "route_id": "18705", "vehicle_id": "19124", "latitude": 49.069332122802734, "longitude": -122.66960144042969, "timestamp": 1768144092, "current_stop_sequence": 23}, {"trip_id": "14901420", "route_id": "6619", "vehicle_id": "18311", "latitude": 49.26353454589844, "longitude": -123.12937927246094, "timestamp": 1768144112, "current_stop_sequence": 29}, {"trip_id": "14831208", "route_id": "6618", "vehicle_id": "2552", "latitude": 49.211082458496094, "longitude": -123.09286499023438, "timestamp": 1768143850, "current_stop_sequence": 1}, {"trip_id": "14904289", "route_id": "6624", "vehicle_id": "2109", "latitude": 49.30073165893555, "longitude": -123.13423156738281, "timestamp": 1768143589, "current_stop_sequence": 50}, {"trip_id": "14844638", "route_id": "16719", "vehicle_id": "21519", "latitude": 49.217098236083984, "longitude": -122.89616394042969, "timestamp": 1768144101, "current_stop_sequence": 4}, {"trip_id": "14904290", "route_id": "6624", "vehicle_id": "2258", "latitude": 49.28670120239258, "longitude": -123.11813354492188, "timestamp": 1768144105, "current_stop_sequence": 44}, {"trip_id": "14853957", "route_id": "30046", "vehicle_id": "24537", "latitude": 49.296600341796875, "longitude": -122.83793640136719, "timestamp": 1768144111, "current_stop_sequence": 27}, {"trip_id": "14853077", "route_id": "30040", "vehicle_id": "21501", "latitude": 49.2801513671875, "longitude": -122.7717514038086, "timestamp": 1768144128, "current_stop_sequence": 21}, {"trip_id": "14863679", "route_id": "6704", "vehicle_id": "19112", "latitude": 49.172401428222656, "longitude": -122.80111694335938, "timestamp": 1768144133, "current_stop_sequence": 6}, {"trip_id": "14886193", "route_id": "6837", "vehicle_id": "9646", "latitude": 49.32401657104492, "longitude": -123.12071990966797, "timestamp": 1768144137, "current_stop_sequence": 41}, {"trip_id": "14902744", "route_id": "6620", "vehicle_id": "2533", "latitude": 49.215782165527344, "longitude": -123.14019775390625, "timestamp": 1768144103, "current_stop_sequence": 11}, {"trip_id": "14855181", "route_id": "22638", "vehicle_id": "16019", "latitude": 49.28166580200195, "longitude": -122.79335021972656, "timestamp": 1768144115, "current_stop_sequence": 35}, {"trip_id": "14886087", "route_id": "6834", "vehicle_id": "25168", "latitude": 49.2041015625, "longitude": -122.87539672851562, "timestamp": 1768144028, "current_stop_sequence": 87}, {"trip_id": "14886343", "route_id": "6841", "vehicle_id": "18164", "latitude": 49.26628112792969, "longitude": -123.00189971923828, "timestamp": 1768144112, "current_stop_sequence": 40}, {"trip_id": "14854924", "route_id": "30050", "vehicle_id": "21502", "latitude": 49.28229904174805, "longitude": -122.80181884765625, "timestamp": 1768144145, "current_stop_sequence": 16}, {"trip_id": "14886084", "route_id": "6834", "vehicle_id": "25152", "latitude": 49.284366607666016, "longitude": -123.1172866821289, "timestamp": 1768144113, "current_stop_sequence": 1}, {"trip_id": "14864177", "route_id": "6705", "vehicle_id": "9684", "latitude": 49.064701080322266, "longitude": -122.8171157836914, "timestamp": 1768144102, "current_stop_sequence": 19}, {"trip_id": "14886083", "route_id": "6834", "vehicle_id": "9642", "latitude": 49.20591735839844, "longitude": -122.91127014160156, "timestamp": 1768144133, "current_stop_sequence": 79}, {"trip_id": "14871089", "route_id": "6722", "vehicle_id": "9542", "latitude": 49.16608428955078, "longitude": -123.13383483886719, "timestamp": 1768143897, "current_stop_sequence": 1}, {"trip_id": "14887447", "route_id": "38311", "vehicle_id": "23005", "latitude": 49.31159973144531, "longitude": -123.08090209960938, "timestamp": 1768144137, "current_stop_sequence": 5}, {"trip_id": "14864264", "route_id": "6705", "vehicle_id": "18371", "latitude": 49.18965148925781, "longitude": -122.8475341796875, "timestamp": 1768144123, "current_stop_sequence": 1}, {"trip_id": "14864271", "route_id": "6705", "vehicle_id": "18135", "latitude": 49.189815521240234, "longitude": -122.84771728515625, "timestamp": 1768144091, "current_stop_sequence": 1}, {"trip_id": "14886194", "route_id": "6837", "vehicle_id": "9766", "latitude": 49.33660125732422, "longitude": -123.03880310058594, "timestamp": 1768144133, "current_stop_sequence": 1}, {"trip_id": "14863221", "route_id": "6703", "vehicle_id": "18142", "latitude": 49.18281555175781, "longitude": -122.89035034179688, "timestamp": 1768144137, "current_stop_sequence": 4}, {"trip_id": "14890009", "route_id": "46604", "vehicle_id": "18035", "latitude": 49.2044677734375, "longitude": -122.87496948242188, "timestamp": 1768144031, "current_stop_sequence": 1}, {"trip_id": "14876987", "route_id": "12940", "vehicle_id": "16122", "latitude": 49.1085319519043, "longitude": -122.65961456298828, "timestamp": 1768144089, "current_stop_sequence": 19}, {"trip_id": "14846340", "route_id": "6649", "vehicle_id": "9499", "latitude": 49.25486755371094, "longitude": -123.00433349609375, "timestamp": 1768144092, "current_stop_sequence": 4}, {"trip_id": "15070020", "route_id": "6692", "vehicle_id": "1201", "latitude": 49.32118225097656, "longitude": -123.02124786376953, "timestamp": 1768144092, "current_stop_sequence": 47}, {"trip_id": "14877313", "route_id": "6741", "vehicle_id": "19430", "latitude": 49.194984436035156, "longitude": -123.12678527832031, "timestamp": 1768144097, "current_stop_sequence": 1}, {"trip_id": "14861989", "route_id": "6698", "vehicle_id": "19418", "latitude": 49.16878128051758, "longitude": -123.13594818115234, "timestamp": 1768144107, "current_stop_sequence": 18}, {"trip_id": "14834237", "route_id": "6623", "vehicle_id": "2203", "latitude": 49.20914840698242, "longitude": -123.11614990234375, "timestamp": 1768144038, "current_stop_sequence": 1}, {"trip_id": "14842531", "route_id": "6642", "vehicle_id": "25112", "latitude": 49.20953369140625, "longitude": -123.11571502685547, "timestamp": 1768144132, "current_stop_sequence": 33}, {"trip_id": "14876942", "route_id": "12940", "vehicle_id": "19143", "latitude": 49.20695114135742, "longitude": -122.66844940185547, "timestamp": 1768144114, "current_stop_sequence": 20}, {"trip_id": "14868677", "route_id": "6715", "vehicle_id": "21412", "latitude": 49.133201599121094, "longitude": -123.08719635009766, "timestamp": 1768144125, "current_stop_sequence": 1}, {"trip_id": "14873608", "route_id": "6728", "vehicle_id": "25135", "latitude": 49.17456817626953, "longitude": -123.13670349121094, "timestamp": 1768144105, "current_stop_sequence": 5}, {"trip_id": "14829545", "route_id": "6615", "vehicle_id": "2225", "latitude": 49.28386688232422, "longitude": -123.12355041503906, "timestamp": 1768144119, "current_stop_sequence": 7}, {"trip_id": "14840299", "route_id": "6637", "vehicle_id": "9449", "latitude": 49.27888488769531, "longitude": -123.12366485595703, "timestamp": 1768144102, "current_stop_sequence": 8}, {"trip_id": "14832892", "route_id": "16718", "vehicle_id": "2202", "latitude": 49.28143310546875, "longitude": -123.1196517944336, "timestamp": 1768144122, "current_stop_sequence": 34}, {"trip_id": "14902743", "route_id": "6620", "vehicle_id": "2551", "latitude": 49.28103256225586, "longitude": -123.12013244628906, "timestamp": 1768144131, "current_stop_sequence": 33}, {"trip_id": "14868622", "route_id": "6715", "vehicle_id": "21401", "latitude": 49.02756881713867, "longitude": -122.80248260498047, "timestamp": 1768144118, "current_stop_sequence": 7}, {"trip_id": "14873687", "route_id": "6728", "vehicle_id": "25127", "latitude": 49.18206787109375, "longitude": -123.13671875, "timestamp": 1768144103, "current_stop_sequence": 31}, {"trip_id": "14870398", "route_id": "6819", "vehicle_id": "24617", "latitude": 49.193233489990234, "longitude": -122.8022689819336, "timestamp": 1768144111, "current_stop_sequence": 1}, {"trip_id": "14861202", "route_id": "6693", "vehicle_id": "23013", "latitude": 49.32553482055664, "longitude": -123.12958526611328, "timestamp": 1768144108, "current_stop_sequence": 5}, {"trip_id": "15070166", "route_id": "6687", "vehicle_id": "1214", "latitude": 49.32096862792969, "longitude": -123.13355255126953, "timestamp": 1768144139, "current_stop_sequence": 15}, {"trip_id": "14858632", "route_id": "6682", "vehicle_id": "9629", "latitude": 49.32210159301758, "longitude": -123.13248443603516, "timestamp": 1768144130, "current_stop_sequence": 31}, {"trip_id": "14851381", "route_id": "6666", "vehicle_id": "16022", "latitude": 49.23466873168945, "longitude": -122.86315155029297, "timestamp": 1768144101, "current_stop_sequence": 5}, {"trip_id": "14846381", "route_id": "6649", "vehicle_id": "25134", "latitude": 49.2001838684082, "longitude": -122.91283416748047, "timestamp": 1768144090, "current_stop_sequence": 1}, {"trip_id": "14875623", "route_id": "23384", "vehicle_id": "19142", "latitude": 49.06821823120117, "longitude": -122.53144836425781, "timestamp": 1768144113, "current_stop_sequence": 30}, {"trip_id": "14875948", "route_id": "18705", "vehicle_id": "19117", "latitude": 49.04668426513672, "longitude": -122.69146728515625, "timestamp": 1768144142, "current_stop_sequence": 21}, {"trip_id": "14876005", "route_id": "18705", "vehicle_id": "9666", "latitude": 49.11801528930664, "longitude": -122.67462921142578, "timestamp": 1768144089, "current_stop_sequence": 1}, {"trip_id": "14839787", "route_id": "6636", "vehicle_id": "16215", "latitude": 49.23965072631836, "longitude": -123.21990203857422, "timestamp": 1768144107, "current_stop_sequence": 6}, {"trip_id": "14874666", "route_id": "6737", "vehicle_id": "16108", "latitude": 49.160133361816406, "longitude": -122.66031646728516, "timestamp": 1768144089, "current_stop_sequence": 22}, {"trip_id": "14861990", "route_id": "6698", "vehicle_id": "21403", "latitude": 49.13169860839844, "longitude": -122.84396362304688, "timestamp": 1768144009, "current_stop_sequence": 1}, {"trip_id": "14887446", "route_id": "38311", "vehicle_id": "19039", "latitude": 49.326133728027344, "longitude": -123.1412353515625, "timestamp": 1768143900, "current_stop_sequence": 10}, {"trip_id": "14836999", "route_id": "6627", "vehicle_id": "8154", "latitude": 49.26628112792969, "longitude": -123.00164794921875, "timestamp": 1768144048, "current_stop_sequence": 1}, {"trip_id": "14850137", "route_id": "6659", "vehicle_id": "14015", "latitude": 49.263668060302734, "longitude": -122.87837982177734, "timestamp": 1768144101, "current_stop_sequence": 22}, {"trip_id": "14864178", "route_id": "6705", "vehicle_id": "18374", "latitude": 49.11220169067383, "longitude": -122.84056854248047, "timestamp": 1768144133, "current_stop_sequence": 27}, {"trip_id": "14887348", "route_id": "38311", "vehicle_id": "23008", "latitude": 49.31364822387695, "longitude": -123.08551788330078, "timestamp": 1768144134, "current_stop_sequence": 5}, {"trip_id": "14855141", "route_id": "22638", "vehicle_id": "16010", "latitude": 49.29276657104492, "longitude": -122.78191375732422, "timestamp": 1768144108, "current_stop_sequence": 11}, {"trip_id": "14842388", "route_id": "6642", "vehicle_id": "9411", "latitude": 49.20320129394531, "longitude": -123.13311767578125, "timestamp": 1768144141, "current_stop_sequence": 1}, {"trip_id": "14875181", "route_id": "6738", "vehicle_id": "19105", "latitude": 49.188716888427734, "longitude": -122.84770202636719, "timestamp": 1768143686, "current_stop_sequence": 29}, {"trip_id": "14877571", "route_id": "11696", "vehicle_id": "25509", "latitude": 49.04133224487305, "longitude": -123.08181762695312, "timestamp": 1768144114, "current_stop_sequence": 27}, {"trip_id": "14852461", "route_id": "30037", "vehicle_id": "21505", "latitude": 49.25645065307617, "longitude": -122.72866821289062, "timestamp": 1768144142, "current_stop_sequence": 11}, {"trip_id": "14854698", "route_id": "30049", "vehicle_id": "21513", "latitude": 49.274898529052734, "longitude": -122.79883575439453, "timestamp": 1768143620, "current_stop_sequence": 18}, {"trip_id": "14830131", "route_id": "6616", "vehicle_id": "2144", "latitude": 49.27938461303711, "longitude": -123.11333465576172, "timestamp": 1768144089, "current_stop_sequence": 14}, {"trip_id": "14901987", "route_id": "11201", "vehicle_id": "18395", "latitude": 49.267948150634766, "longitude": -123.24828338623047, "timestamp": 1768144090, "current_stop_sequence": 1}, {"trip_id": "14836885", "route_id": "6627", "vehicle_id": "8142", "latitude": 49.26771545410156, "longitude": -123.247314453125, "timestamp": 1768144099, "current_stop_sequence": 1}, {"trip_id": "14837256", "route_id": "6628", "vehicle_id": "9729", "latitude": 49.244415283203125, "longitude": -123.04451751708984, "timestamp": 1768144102, "current_stop_sequence": 1}, {"trip_id": "14847439", "route_id": "6651", "vehicle_id": "9769", "latitude": 49.226383209228516, "longitude": -123.00469970703125, "timestamp": 1768144105, "current_stop_sequence": 28}, {"trip_id": "14861945", "route_id": "6698", "vehicle_id": "19429", "latitude": 49.177066802978516, "longitude": -123.1010971069336, "timestamp": 1768144088, "current_stop_sequence": 5}, {"trip_id": "14845951", "route_id": "32799", "vehicle_id": "24145", "latitude": 49.220184326171875, "longitude": -122.97286987304688, "timestamp": 1768144139, "current_stop_sequence": 9}, {"trip_id": "14886895", "route_id": "37808", "vehicle_id": "18039", "latitude": 49.193931579589844, "longitude": -122.80525207519531, "timestamp": 1768143875, "current_stop_sequence": 1}, {"trip_id": "14887868", "route_id": "37809", "vehicle_id": "18056", "latitude": 49.21916580200195, "longitude": -122.59626770019531, "timestamp": 1768143984, "current_stop_sequence": 7}, {"trip_id": "14887946", "route_id": "37809", "vehicle_id": "18059", "latitude": 49.227901458740234, "longitude": -122.68111419677734, "timestamp": 1768144101, "current_stop_sequence": 3}, {"trip_id": "14878932", "route_id": "6749", "vehicle_id": "18206", "latitude": 49.24021530151367, "longitude": -122.712646484375, "timestamp": 1768144100, "current_stop_sequence": 29}, {"trip_id": "14888733", "route_id": "37810", "vehicle_id": "18044", "latitude": 49.25394821166992, "longitude": -123.24136352539062, "timestamp": 1768143819, "current_stop_sequence": 16}, {"trip_id": "14875092", "route_id": "6738", "vehicle_id": "18146", "latitude": 49.180450439453125, "longitude": -122.84378051757812, "timestamp": 1768144125, "current_stop_sequence": 5}, {"trip_id": "14872593", "route_id": "34542", "vehicle_id": "9543", "latitude": 49.167701721191406, "longitude": -123.13556671142578, "timestamp": 1768144122, "current_stop_sequence": 1}, {"trip_id": "14844477", "route_id": "6645", "vehicle_id": "24143", "latitude": 49.20555114746094, "longitude": -122.91069793701172, "timestamp": 1768144129, "current_stop_sequence": 2}, {"trip_id": "14836937", "route_id": "6627", "vehicle_id": "21008", "latitude": 49.24883270263672, "longitude": -123.01961517333984, "timestamp": 1768144109, "current_stop_sequence": 9}, {"trip_id": "14847371", "route_id": "6651", "vehicle_id": "9625", "latitude": 49.28110122680664, "longitude": -123.004150390625, "timestamp": 1768144141, "current_stop_sequence": 20}, {"trip_id": "14886894", "route_id": "37808", "vehicle_id": "18008", "latitude": 49.181251525878906, "longitude": -122.845703125, "timestamp": 1768144132, "current_stop_sequence": 8}, {"trip_id": "14890007", "route_id": "46604", "vehicle_id": "18013", "latitude": 49.13391876220703, "longitude": -122.88140106201172, "timestamp": 1768144137, "current_stop_sequence": 9}, {"trip_id": "14889933", "route_id": "46604", "vehicle_id": "18034", "latitude": 49.17720031738281, "longitude": -122.8900146484375, "timestamp": 1768144091, "current_stop_sequence": 10}, {"trip_id": "15070253", "route_id": "6687", "vehicle_id": "1206", "latitude": 49.28561782836914, "longitude": -123.1229476928711, "timestamp": 1768144113, "current_stop_sequence": 3}, {"trip_id": "14836886", "route_id": "6627", "vehicle_id": "8120", "latitude": 49.248817443847656, "longitude": -123.1094970703125, "timestamp": 1768144108, "current_stop_sequence": 32}, {"trip_id": "14839786", "route_id": "6636", "vehicle_id": "12023", "latitude": 49.22606658935547, "longitude": -123.11640167236328, "timestamp": 1768144120, "current_stop_sequence": 30}, {"trip_id": "14875713", "route_id": "23384", "vehicle_id": "24139", "latitude": 49.152034759521484, "longitude": -122.76544952392578, "timestamp": 1768144141, "current_stop_sequence": 8}, {"trip_id": "14875657", "route_id": "23384", "vehicle_id": "18158", "latitude": 49.17509841918945, "longitude": -122.82496643066406, "timestamp": 1768144108, "current_stop_sequence": 3}, {"trip_id": "14871095", "route_id": "6722", "vehicle_id": "9413", "latitude": 49.12678146362305, "longitude": -123.1872329711914, "timestamp": 1768143852, "current_stop_sequence": 31}, {"trip_id": "14902814", "route_id": "6620", "vehicle_id": "2526", "latitude": 49.25728225708008, "longitude": -123.13887023925781, "timestamp": 1768144097, "current_stop_sequence": 12}]